Workbook

Sheet README
G1: GovTech Maturity Index (GTMI) 2025 Update
B3: Workbook sheets | D3: Contents
B4: README | D4: Presents the contents of the GovTech Dataset and introduces the source data, calculation of the GTMI groups, and other aspects
B5: GTMI_Data | D5: 2025 GTMI Dataset including survey responses and remotely collected data (together with 2020 and 2022 data)
B6: GTMI_Groups | D6: 2025 GTMI Groups, component scores and the details of calculations
B7: Stats | D7: Visuals presenting the int'l outlook, regional, income level, borrower, and FCS distributions, as well as economy/indicator details
B8: Regions | D8: Subset of GTMI dataset including 163 countries in seven World Bank regions
B9: Trends | D9: Historical trend lines for selected key indicators
B10: Metadata | D10: Country data sheet; Explanation of the data fields in the GTMI_Data sheet
B11: External | D11: 2024 UN EGDI (I-16, I-18, I-44); e-Participation Index (I-27); 2024 ITU GCI (I-43)
B12: Economies | D12: Alphabetic list of 198 economies, together with the list of Fragility and Conflict-affected Situations (FCS)
B14: 2025 GTMI Survey Data
B15:  2025 GTMI survey data is presented in the GTMI_Data sheet (together with 2020 and 2022 data covering 198 economies)
B17:  Total number of economies included in the 2025 dataset is 197 (Nicaragua didn't authorize the collection of their data)
B18:  The GTMI survey includes 43 updated/extended GovTech indicators measuring the maturity of four GovTech focus areas
B19:  Additionally, 5 relevant external indicators measured by other relevant indexes, including:
B20: ⦁ All three components of the United Nations (UN) e-Government Development Index (EGDI) + UN e-Participation Index (EPI)
B21: ⦁ The ITU’s Global Cybersecurity Index (GCI)
B23:  The GTMI is the simple average of the normalized scores of four components:
B24: ⦁ CGSI - Core Government Systems Index (17 indicators) captures the key aspects of a whole-of-government approach
B25: ⦁ PSDI - Public Service Delivery Index (9 indicators) presents the state of online portals, e-filing services, e-payment capabilities and more
B26: ⦁ DCEI - Digital Citizen Engagement Index (6 indicators) measures aspects of public participation platforms, citizen feedback, and open gov/data portals
B27: ⦁ GTEI - GovTech Enablers Index (16 indicators) captures strategy, institutions, and regulations, as well as digital skills and innovation programs
B29:  48 key indicators and related sub-indicators are presented in columns D to PK (424 data fields)

Sheet GTMI_Data
A1: Year | B1: Code | C1: Economy | D1: I-1 | E1: I-1.1 | F1: I-1.2 | G1: I-1.3 | H1: I-1.4 | I1: I-1.5 | J1: I-1.6 | K1: I-1.6.1 | L1: I-1.7 | M1: I-1.8 | N1: I-1.9 | O1: I-1.9.1 | P1: I-1.9.2 | Q1: I-2 | R1: I-2.1 | S1: I-2.2 | T1: I-2.3
A2: 2020 | B2: AFG | C2: Afghanistan | D2: 0 | E2: - | F2: - | G2: - | H2: New | I2: New | J2: New | K2: New | L2: New | M2: New | N2: New | O2: New | P2: New | Q2: 0 | R2: - | S2: - | T2: -
A3: 2022 | B3: AFG | C3: Afghanistan | D3: 0 | E3: - | F3: - | G3: - | H3: 0 | I3: - | J3: 0 | K3: - | L3: 0 | M3: 0 | N3: 0 | O3: New | P3: - | Q3: 0 | R3: - | S3: - | T3: -
A4: 2025 | B4: AFG | C4: Afghanistan | D4: 0 | E4: - | F4: - | G4: - | H4: 0 | I4: - | J4: 0 | K4: - | L4: 0 | M4: 0 | N4: 0 | O4: 0 | P4: - | Q4: 0 | R4: - | S4: - | T4: -
A5: 2020 | B5: ALB | C5: Albania | D5: 1 | E5: Government Data OneDrive | F5: https://akshi.gov.al/sherbime/sherbimi-onedrive/ | G5: 2014 | H5: New | I5: New | J5: New | K5: New | L5: New | M5: New | N5: New | O5: New | P5: New | Q5: 0 | R5: - | S5: - | T5: -
A6: 2022 | B6: ALB | C6: Albania | D6: 1 | E6: Government Cloud | F6: 2022-2026 Digital Agenda | G6: 2022 | H6: 2 | I6: National Agency of Information Society | J6: 1 | K6: In progress | L6: 3 | M6: 2 | N6: 0 | O6: New | P6: - | Q6: 0 | R6: - | S6: - | T6: -
A7: 2025 | B7: ALB | C7: Albania | D7: 2 | E7: Government Hybrid Cloud | F7: https://akshi.gov.al/sherbime/sherbime-te-perqendruara-qeveritare/ | G7: 2022 | H7: 2 | I7: National Agency of Information Society | J7: 1 | K7: https://idp.al/wp-content/uploads/2025/02/ligj-2024-12-19-124-1.pdf | L7: 3 | M7: 2 | N7: 1 | O7: 4 | P7: https://akshi.gov.al/sherbime/sherbime-te-perqendruara-qeveritare/ | Q7: 2 | R7: Law No. 43/2023 “On Electronic Governance” | S7: https://akshi.gov.al/wp-content/uploads/2024/11/ligj-2023-06-15-43-i-pe%CC%88rdite%CC%88suar.pdf | T7: 2023
A8: 2020 | B8: DZA | C8: Algeria | D8: 0 | E8: - | F8: - | G8: - | H8: New | I8: New | J8: New | K8: New | L8: New | M8: New | N8: New | O8: New | P8: New | Q8: 0 | R8: - | S8: - | T8: -
A9: 2022 | B9: DZA | C9: Algeria | D9: 1 | E9: Government Cloud | F9: - | G9: 2023 | H9: 1 | I9: - | J9: 3 | K9: In progress | L9: 4 | M9: 0 | N9: 0 | O9: New | P9: - | Q9: 0 | R9: - | S9: - | T9: -
A10: 2025 | B10: DZA | C10: Algeria | D10: 1 | E10: Government Cloud | F10: https://hcn.dz/SNTN-En.pdf | G10: 2026 | H10: 3 | I10: High Commission for Digitalization | J10: 1 | K10: https://lalgerieaujourdhui.dz/inauguration-dun-cloud-national-dedie-au-stockage-local-des-donnees-un-grand-pas-vers-la-souverainete-numerique/#:~:text=Inauguration%20d'un%20Cloud%20national%20d%C3%A9di%C3%A9%20au%20stockage,vers%20la%20souverainet%C3%A9%20num%C3%A9rique%20%2D%20L'Alg%C3%A9rie%20Aujourd'hui.&text=Avec%20cette%20nouvelle%20infrastructure%2C%20l'Alg%C3%A9rie%20se%20donne,garantissant%20une%20meilleure%20disponibilit%C3%A9%20des%20services%20num%C3%A9riques. | L10: 4 | M10: 1 | N10: 0 | O10: 0 | P10: - | Q10: 1 | R10: National Strategy for Digital Transformation in ALGERIA | S10: https://www.hcn.dz | T10: 2026
A11: 2020 | B11: AND | C11: Andorra | D11: 0 | E11: - | F11: - | G11: - | H11: New | I11: New | J11: New | K11: New | L11: New | M11: New | N11: New | O11: New | P11: New | Q11: 0 | R11: - | S11: - | T11: -
A12: 2022 | B12: AND | C12: Andorra | D12: 0 | E12: - | F12: - | G12: - | H12: 0 | I12: - | J12: 0 | K12: - | L12: 0 | M12: 0 | N12: 0 | O12: New | P12: - | Q12: 0 | R12: - | S12: - | T12: -
A13: 2025 | B13: AND | C13: Andorra | D13: 0 | E13: - | F13: - | G13: - | H13: 0 | I13: - | J13: 0 | K13: - | L13: 0 | M13: 0 | N13: 0 | O13: 0 | P13: - | Q13: 0 | R13: - | S13: - | T13: -
A14: 2020 | B14: AGO | C14: Angola | D14: 0 | E14: - | F14: - | G14: - | H14: New | I14: New | J14: New | K14: New | L14: New | M14: New | N14: New | O14: New | P14: New | Q14: 0 | R14: - | S14: - | T14: -
A15: 2022 | B15: AGO | C15: Angola | D15: 0 | E15: - | F15: - | G15: - | H15: 0 | I15: - | J15: 0 | K15: - | L15: 0 | M15: 0 | N15: 0 | O15: New | P15: - | Q15: 0 | R15: - | S15: - | T15: -
A16: 2025 | B16: AGO | C16: Angola | D16: 0 | E16: - | F16: - | G16: - | H16: 0 | I16: - | J16: 0 | K16: - | L16: 0 | M16: 0 | N16: 0 | O16: 0 | P16: - | Q16: 2 | R16: Arquitectura de Referência do Governo Electrónico | S16: https://ima.gov.ao/fotos/frontend_4/editor2/agenda_governoao27.pdf | T16: 2024
A17: 2020 | B17: ATG | C17: Antigua and Barbuda | D17: 0 | E17: - | F17: - | G17: - | H17: New | I17: New | J17: New | K17: New | L17: New | M17: New | N17: New | O17: New | P17: New | Q17: 0 | R17: - | S17: - | T17: -
A18: 2022 | B18: ATG | C18: Antigua and Barbuda | D18: 1 | E18: Azure and Private Gov-Cloud | F18: No URL at the moment | G18: 2017 | H18: 3 | I18: Ministry of Information | J18: 3 | K18: Not defined | L18: 3 | M18: 1 | N18: 0 | O18: New | P18: - | Q18: 0 | R18: - | S18: - | T18: -
A19: 2025 | B19: ATG | C19: Antigua and Barbuda | D19: 0 | E19: - | F19: - | G19: - | H19: 0 | I19: - | J19: 0 | K19: - | L19: 0 | M19: 0 | N19: 0 | O19: 0 | P19: - | Q19: 0 | R19: - | S19: - | T19: -
A20: 2020 | B20: ARG | C20: Argentina | D20: 2 | E20: ARSAT | F20: https://www.arsat.com.ar/centro-nacional-de-datos | G20: 2015 | H20: New | I20: New | J20: New | K20: New | L20: New | M20: New | N20: New | O20: New | P20: New | Q20: 0 | R20: - | S20: - | T20: -
A21: 2022 | B21: ARG | C21: Argentina | D21: 2 | E21: ARSAT | F21: https://www.arsat.com.ar/centro-nacional-de-datos/proyectos/nube-publica-nacional/https://www.arsat.com.ar/ | G21: 2015 | H21: 1 | I21: Empresa Argentina de Soluciones Satelitales | J21: 0 | K21: - | L21: 3 | M21: 2 | N21: 0 | O21: New | P21: - | Q21: 0 | R21: - | S21: - | T21: -
A22: 2025 | B22: ARG | C22: Argentina | D22: 2 | E22: Nube Pública Nacional | F22: https://nube.arsat.com.ar/ | G22: 2021 | H22: 1 | I22: Empresa Argentina de Soluciones Satelitales | J22: 1 | K22: https://www.arsat.com.ar/soluciones-comerciales/nube-y-datacenter/ | L22: 4 | M22: 2 | N22: 1 | O22: 4 | P22: https://www.bnamericas.com/en/news/more-than-95-of-the-federal-fiber-optic-network-is-already-illuminated#:~:text=Until%20the%20launch%20and%20commissioning,Legal%2C%20Financial%20and%20Insurance%20industries. | Q22: 0 | R22: - | S22: - | T22: -
A23: 2020 | B23: ARM | C23: Armenia | D23: 0 | E23: - | F23: - | G23: - | H23: New | I23: New | J23: New | K23: New | L23: New | M23: New | N23: New | O23: New | P23: New | Q23: 0 | R23: - | S23: - | T23: -
A24: 2022 | B24: ARM | C24: Armenia | D24: 1 | E24: Government Cloud Platform | F24: There is no Cloud Platform Strategy yet | G24: 2019 | H24: 3 | I24: EKENG CJSC | J24: 0 | K24: - | L24: 4 | M24: 2 | N24: 0 | O24: New | P24: - | Q24: 1 | R24: Government Corporate Network and Data Center | S24: https://www.ekeng.am/en/sub/e_manage | T24: 2012
A25: 2025 | B25: ARM | C25: Armenia | D25: 1 | E25: Government Multi-Cloud Platform | F25: https://www.irtek.am/views/act.aspx?aid=125914 | G25: 2026 | H25: 3 | I25: ISAA, EKENG CJSC | J25: 3 | K25: https://www.irtek.am/views/act.aspx?aid=125914 | L25: 4 | M25: 1 | N25: 0 | O25: 0 | P25: - | Q25: 2 | R25: Enterprise Architecture Framework | S25: https://docs.google.com/document/d/1CM82tNIYWVJW2xcmtuJ5F2dJI4mNIlrM/edit?tab=t.0 | T25: 2023
A26: 2020 | B26: AUS | C26: Australia | D26: 2 | E26: Cloud.gov.au | F26: https://cloud.gov.au/ | G26: 2018 | H26: New | I26: New | J26: New | K26: New | L26: New | M26: New | N26: New | O26: New | P26: New | Q26: 2 | R26: Open Architecture | S26: https://www.dta.gov.au/our-projects/digital-service-platforms-strategy/digital-platforms-strategic-roadmap | T26: 2019
A27: 2022 | B27: AUS | C27: Australia | D27: 2 | E27: Secure Cloud Strategy | F27: https://www.dta.gov.au/our-projects/secure-cloud-strategy | G27: 2018 | H27: 1 | I27: There are Cloud platforms managed by multiple providers, the largest are hosted by AWS and Microsoft under whole of Government agreements centrally negotiated by the Digital Transformation Agency. | J27: 3 | K27: https://www.dta.gov.au/our-projects/hosting-strategy/hosting-certification-framework | L27: 4 | M27: 1 | N27: 1 | O27: New | P27: Not published | Q27: 2 | R27: The Australian Government Architecture | S27: https://www.dta.gov.au/whole-government-architecture | T27: 2021
A28: 2025 | B28: AUS | C28: Australia | D28: 2 | E28: Secure Cloud Strategy | F28: https://architecture.digital.gov.au/secure-cloud-strategy | G28: 2018 | H28: 3 | I28: Digital Transformation Agency (DTA) | J28: 3 | K28: https://www.hostingcertification.gov.au/ | L28: 4 | M28: 1 | N28: 1 | O28: 4 | P28: https://www.digital.gov.au/sites/default/files/documents/2025-03/2025%20Major%20Digital%20Projects%20Report.pdf | Q28: 2 | R28: Australian Government Architecture | S28: https://architecture.digital.gov.au/ | T28: 2019
A29: 2020 | B29: AUT | C29: Austria | D29: 2 | E29: GovCloud | F29: https://www.brz.gv.at/en/what_we_do/our_business/cloud-solutions.html | G29: 2013 | H29: New | I29: New | J29: New | K29: New | L29: New | M29: New | N29: New | O29: New | P29: New | Q29: 2 | R29: Digital Austria | S29: https://www.bmdw.gv.at/Themen/Digitalisierung/Digitales-Oesterreich.html | T29: 2018
A30: 2022 | B30: AUT | C30: Austria | D30: 2 | E30: GovCloud + Ö-Cloud initiative | F30: https://www.brz.gv.at/en/what_we_do/our_business/cloud-solutions.html | G30: 2013 | H30: 1 | I30: Austrian Federal Computing Center (short: BRZ as abbreviated from the German name Bundesrechenzentrum) | J30: 1 | K30: https://www.brz.gv.at/was-wir-tun/geschaeftsfelder/cloud-solutions.html | L30: 1 | M30: 2 | N30: 1 | O30: New | P30: Internal usage only | Q30: 2 | R30: Digital Austria | S30: https://www.bmdw.gv.at/Themen/Digitalisierung/Digitales-Oesterreich.html | T30: 2018

Sheet GTMI_Groups
A1: Year | B1: Code | C1: Economy | D1: Grp | E1: GTMI | F1: GT1 | G1: CGSI | H1: GT2 | I1: PSDI | J1: GT3 | K1: DCEI | L1: GT4 | M1: GTEI | N1: I-1 | O1: I-1.4 | P1: I-1.6 | Q1: I-1.7 | R1: I-1.8 | S1: I-1.9 | T1: I-1.9.1
A2: 2025 | B2: =VLOOKUP($C2,Economies!$C$2:$E$199,2,FALSE) -> AFG | C2: Afghanistan | D2: =IF(E2>=$B$202,"A",IF(E2>=$B$203,"B",IF(E2>=$B$204,"C","D"))) -> D | E2: =AVERAGE(G2,I2,K2,M2) -> 0.12100789 | F2: =IF(G2>=$B$202,"A",IF(G2>=$B$203,"B",IF(G2>=$B$204,"C","D"))) -> D | G2: =SUM(N2:DL2)/$F$208 -> 0.16431801 | H2: =IF(I2>=$B$202,"A",IF(I2>=$B$203,"B",IF(I2>=$B$204,"C","D"))) -> C | I2: =SUM(DM2:FL2)/$H$208 -> 0.27531004 | J2: =IF(K2>=$B$202,"A",IF(K2>=$B$203,"B",IF(K2>=$B$204,"C","D"))) -> D | K2: =SUM(FM2:GR2)/$J$208 -> 0.019777444 | L2: =IF(M2>=$B$202,"A",IF(M2>=$B$203,"B",IF(M2>=$B$204,"C","D"))) -> D | M2: =SUM(GS2:JM2)/$L$208 -> 0.024626087 | N2: =VLOOKUP($B2,GTMI_Data!$B$2:$PK$595,N$211,FALSE)*N$215 -> 0 | O2: =IF(VLOOKUP($B2,GTMI_Data!$B$2:$PK$595,O$211,FALSE)=0,0,1) -> 0 | P2: =IF(VLOOKUP($B2,GTMI_Data!$B$2:$PK$595,P$211,FALSE)=0,0,1) -> 0 | Q2: =IF(VLOOKUP($B2,GTMI_Data!$B$2:$PK$595,Q$211,FALSE)=0,0,1) -> 0 | R2: =IF(VLOOKUP($B2,GTMI_Data!$B$2:$PK$595,R$211,FALSE)=0,0,1) -> 0 | S2: =VLOOKUP($B2,GTMI_Data!$B$2:$PK$595,S$211,FALSE)*S$215 -> 0 | T2: =IF(VLOOKUP($B2,GTMI_Data!$B$2:$PK$595,T$211,FALSE)=0,0,1) -> 0
A3: 2025 | B3: =VLOOKUP($C3,Economies!$C$2:$E$199,2,FALSE) -> ALB | C3: Albania | D3: =IF(E3>=$B$202,"A",IF(E3>=$B$203,"B",IF(E3>=$B$204,"C","D"))) -> A | E3: =AVERAGE(G3,I3,K3,M3) -> 0.93852735 | F3: =IF(G3>=$B$202,"A",IF(G3>=$B$203,"B",IF(G3>=$B$204,"C","D"))) -> A | G3: =SUM(N3:DL3)/$F$208 -> 0.9307039 | H3: =IF(I3>=$B$202,"A",IF(I3>=$B$203,"B",IF(I3>=$B$204,"C","D"))) -> A | I3: =SUM(DM3:FL3)/$H$208 -> 0.94100343 | J3: =IF(K3>=$B$202,"A",IF(K3>=$B$203,"B",IF(K3>=$B$204,"C","D"))) -> A | K3: =SUM(FM3:GR3)/$J$208 -> 0.95055639 | L3: =IF(M3>=$B$202,"A",IF(M3>=$B$203,"B",IF(M3>=$B$204,"C","D"))) -> A | M3: =SUM(GS3:JM3)/$L$208 -> 0.93184568 | N3: =VLOOKUP($B3,GTMI_Data!$B$2:$PK$595,N$211,FALSE)*N$215 -> 12 | O3: =IF(VLOOKUP($B3,GTMI_Data!$B$2:$PK$595,O$211,FALSE)=0,0,1) -> 1 | P3: =IF(VLOOKUP($B3,GTMI_Data!$B$2:$PK$595,P$211,FALSE)=0,0,1) -> 1 | Q3: =IF(VLOOKUP($B3,GTMI_Data!$B$2:$PK$595,Q$211,FALSE)=0,0,1) -> 1 | R3: =IF(VLOOKUP($B3,GTMI_Data!$B$2:$PK$595,R$211,FALSE)=0,0,1) -> 1 | S3: =VLOOKUP($B3,GTMI_Data!$B$2:$PK$595,S$211,FALSE)*S$215 -> 2 | T3: =IF(VLOOKUP($B3,GTMI_Data!$B$2:$PK$595,T$211,FALSE)=0,0,1) -> 1
A4: 2025 | B4: =VLOOKUP($C4,Economies!$C$2:$E$199,2,FALSE) -> DZA | C4: Algeria | D4: =IF(E4>=$B$202,"A",IF(E4>=$B$203,"B",IF(E4>=$B$204,"C","D"))) -> B | E4: =AVERAGE(G4,I4,K4,M4) -> 0.55487551 | F4: =IF(G4>=$B$202,"A",IF(G4>=$B$203,"B",IF(G4>=$B$204,"C","D"))) -> B | G4: =SUM(N4:DL4)/$F$208 -> 0.54462573 | H4: =IF(I4>=$B$202,"A",IF(I4>=$B$203,"B",IF(I4>=$B$204,"C","D"))) -> B | I4: =SUM(DM4:FL4)/$H$208 -> 0.68150204 | J4: =IF(K4>=$B$202,"A",IF(K4>=$B$203,"B",IF(K4>=$B$204,"C","D"))) -> C | K4: =SUM(FM4:GR4)/$J$208 -> 0.39334737 | L4: =IF(M4>=$B$202,"A",IF(M4>=$B$203,"B",IF(M4>=$B$204,"C","D"))) -> B | M4: =SUM(GS4:JM4)/$L$208 -> 0.60002691 | N4: =VLOOKUP($B4,GTMI_Data!$B$2:$PK$595,N$211,FALSE)*N$215 -> 6 | O4: =IF(VLOOKUP($B4,GTMI_Data!$B$2:$PK$595,O$211,FALSE)=0,0,1) -> 1 | P4: =IF(VLOOKUP($B4,GTMI_Data!$B$2:$PK$595,P$211,FALSE)=0,0,1) -> 1 | Q4: =IF(VLOOKUP($B4,GTMI_Data!$B$2:$PK$595,Q$211,FALSE)=0,0,1) -> 1 | R4: =IF(VLOOKUP($B4,GTMI_Data!$B$2:$PK$595,R$211,FALSE)=0,0,1) -> 1 | S4: =VLOOKUP($B4,GTMI_Data!$B$2:$PK$595,S$211,FALSE)*S$215 -> 0 | T4: =IF(VLOOKUP($B4,GTMI_Data!$B$2:$PK$595,T$211,FALSE)=0,0,1) -> 0
A5: 2025 | B5: =VLOOKUP($C5,Economies!$C$2:$E$199,2,FALSE) -> AND | C5: Andorra | D5: =IF(E5>=$B$202,"A",IF(E5>=$B$203,"B",IF(E5>=$B$204,"C","D"))) -> C | E5: =AVERAGE(G5,I5,K5,M5) -> 0.39016981 | F5: =IF(G5>=$B$202,"A",IF(G5>=$B$203,"B",IF(G5>=$B$204,"C","D"))) -> C | G5: =SUM(N5:DL5)/$F$208 -> 0.33226905 | H5: =IF(I5>=$B$202,"A",IF(I5>=$B$203,"B",IF(I5>=$B$204,"C","D"))) -> B | I5: =SUM(DM5:FL5)/$H$208 -> 0.56111412 | J5: =IF(K5>=$B$202,"A",IF(K5>=$B$203,"B",IF(K5>=$B$204,"C","D"))) -> D | K5: =SUM(FM5:GR5)/$J$208 -> 0.20413233 | L5: =IF(M5>=$B$202,"A",IF(M5>=$B$203,"B",IF(M5>=$B$204,"C","D"))) -> C | M5: =SUM(GS5:JM5)/$L$208 -> 0.46316375 | N5: =VLOOKUP($B5,GTMI_Data!$B$2:$PK$595,N$211,FALSE)*N$215 -> 0 | O5: =IF(VLOOKUP($B5,GTMI_Data!$B$2:$PK$595,O$211,FALSE)=0,0,1) -> 0 | P5: =IF(VLOOKUP($B5,GTMI_Data!$B$2:$PK$595,P$211,FALSE)=0,0,1) -> 0 | Q5: =IF(VLOOKUP($B5,GTMI_Data!$B$2:$PK$595,Q$211,FALSE)=0,0,1) -> 0 | R5: =IF(VLOOKUP($B5,GTMI_Data!$B$2:$PK$595,R$211,FALSE)=0,0,1) -> 0 | S5: =VLOOKUP($B5,GTMI_Data!$B$2:$PK$595,S$211,FALSE)*S$215 -> 0 | T5: =IF(VLOOKUP($B5,GTMI_Data!$B$2:$PK$595,T$211,FALSE)=0,0,1) -> 0
A6: 2025 | B6: =VLOOKUP($C6,Economies!$C$2:$E$199,2,FALSE) -> AGO | C6: Angola | D6: =IF(E6>=$B$202,"A",IF(E6>=$B$203,"B",IF(E6>=$B$204,"C","D"))) -> B | E6: =AVERAGE(G6,I6,K6,M6) -> 0.59293688 | F6: =IF(G6>=$B$202,"A",IF(G6>=$B$203,"B",IF(G6>=$B$204,"C","D"))) -> B | G6: =SUM(N6:DL6)/$F$208 -> 0.69489029 | H6: =IF(I6>=$B$202,"A",IF(I6>=$B$203,"B",IF(I6>=$B$204,"C","D"))) -> A | I6: =SUM(DM6:FL6)/$H$208 -> 0.76534596 | J6: =IF(K6>=$B$202,"A",IF(K6>=$B$203,"B",IF(K6>=$B$204,"C","D"))) -> C | K6: =SUM(FM6:GR6)/$J$208 -> 0.33278797 | L6: =IF(M6>=$B$202,"A",IF(M6>=$B$203,"B",IF(M6>=$B$204,"C","D"))) -> B | M6: =SUM(GS6:JM6)/$L$208 -> 0.5787233 | N6: =VLOOKUP($B6,GTMI_Data!$B$2:$PK$595,N$211,FALSE)*N$215 -> 0 | O6: =IF(VLOOKUP($B6,GTMI_Data!$B$2:$PK$595,O$211,FALSE)=0,0,1) -> 0 | P6: =IF(VLOOKUP($B6,GTMI_Data!$B$2:$PK$595,P$211,FALSE)=0,0,1) -> 0 | Q6: =IF(VLOOKUP($B6,GTMI_Data!$B$2:$PK$595,Q$211,FALSE)=0,0,1) -> 0 | R6: =IF(VLOOKUP($B6,GTMI_Data!$B$2:$PK$595,R$211,FALSE)=0,0,1) -> 0 | S6: =VLOOKUP($B6,GTMI_Data!$B$2:$PK$595,S$211,FALSE)*S$215 -> 0 | T6: =IF(VLOOKUP($B6,GTMI_Data!$B$2:$PK$595,T$211,FALSE)=0,0,1) -> 0
A7: 2025 | B7: =VLOOKUP($C7,Economies!$C$2:$E$199,2,FALSE) -> ATG | C7: Antigua and Barbuda | D7: =IF(E7>=$B$202,"A",IF(E7>=$B$203,"B",IF(E7>=$B$204,"C","D"))) -> D | E7: =AVERAGE(G7,I7,K7,M7) -> 0.19382978 | F7: =IF(G7>=$B$202,"A",IF(G7>=$B$203,"B",IF(G7>=$B$204,"C","D"))) -> C | G7: =SUM(N7:DL7)/$F$208 -> 0.35490091 | H7: =IF(I7>=$B$202,"A",IF(I7>=$B$203,"B",IF(I7>=$B$204,"C","D"))) -> D | I7: =SUM(DM7:FL7)/$H$208 -> 0.16733845 | J7: =IF(K7>=$B$202,"A",IF(K7>=$B$203,"B",IF(K7>=$B$204,"C","D"))) -> D | K7: =SUM(FM7:GR7)/$J$208 -> 0.061804511 | L7: =IF(M7>=$B$202,"A",IF(M7>=$B$203,"B",IF(M7>=$B$204,"C","D"))) -> D | M7: =SUM(GS7:JM7)/$L$208 -> 0.19127524 | N7: =VLOOKUP($B7,GTMI_Data!$B$2:$PK$595,N$211,FALSE)*N$215 -> 0 | O7: =IF(VLOOKUP($B7,GTMI_Data!$B$2:$PK$595,O$211,FALSE)=0,0,1) -> 0 | P7: =IF(VLOOKUP($B7,GTMI_Data!$B$2:$PK$595,P$211,FALSE)=0,0,1) -> 0 | Q7: =IF(VLOOKUP($B7,GTMI_Data!$B$2:$PK$595,Q$211,FALSE)=0,0,1) -> 0 | R7: =IF(VLOOKUP($B7,GTMI_Data!$B$2:$PK$595,R$211,FALSE)=0,0,1) -> 0 | S7: =VLOOKUP($B7,GTMI_Data!$B$2:$PK$595,S$211,FALSE)*S$215 -> 0 | T7: =IF(VLOOKUP($B7,GTMI_Data!$B$2:$PK$595,T$211,FALSE)=0,0,1) -> 0
A8: 2025 | B8: =VLOOKUP($C8,Economies!$C$2:$E$199,2,FALSE) -> ARG | C8: Argentina | D8: =IF(E8>=$B$202,"A",IF(E8>=$B$203,"B",IF(E8>=$B$204,"C","D"))) -> A | E8: =AVERAGE(G8,I8,K8,M8) -> 0.75305889 | F8: =IF(G8>=$B$202,"A",IF(G8>=$B$203,"B",IF(G8>=$B$204,"C","D"))) -> A | G8: =SUM(N8:DL8)/$F$208 -> 0.78884017 | H8: =IF(I8>=$B$202,"A",IF(I8>=$B$203,"B",IF(I8>=$B$204,"C","D"))) -> A | I8: =SUM(DM8:FL8)/$H$208 -> 0.90659494 | J8: =IF(K8>=$B$202,"A",IF(K8>=$B$203,"B",IF(K8>=$B$204,"C","D"))) -> B | K8: =SUM(FM8:GR8)/$J$208 -> 0.64001805 | L8: =IF(M8>=$B$202,"A",IF(M8>=$B$203,"B",IF(M8>=$B$204,"C","D"))) -> B | M8: =SUM(GS8:JM8)/$L$208 -> 0.67678243 | N8: =VLOOKUP($B8,GTMI_Data!$B$2:$PK$595,N$211,FALSE)*N$215 -> 12 | O8: =IF(VLOOKUP($B8,GTMI_Data!$B$2:$PK$595,O$211,FALSE)=0,0,1) -> 1 | P8: =IF(VLOOKUP($B8,GTMI_Data!$B$2:$PK$595,P$211,FALSE)=0,0,1) -> 1 | Q8: =IF(VLOOKUP($B8,GTMI_Data!$B$2:$PK$595,Q$211,FALSE)=0,0,1) -> 1 | R8: =IF(VLOOKUP($B8,GTMI_Data!$B$2:$PK$595,R$211,FALSE)=0,0,1) -> 1 | S8: =VLOOKUP($B8,GTMI_Data!$B$2:$PK$595,S$211,FALSE)*S$215 -> 2 | T8: =IF(VLOOKUP($B8,GTMI_Data!$B$2:$PK$595,T$211,FALSE)=0,0,1) -> 1
A9: 2025 | B9: =VLOOKUP($C9,Economies!$C$2:$E$199,2,FALSE) -> ARM | C9: Armenia | D9: =IF(E9>=$B$202,"A",IF(E9>=$B$203,"B",IF(E9>=$B$204,"C","D"))) -> A | E9: =AVERAGE(G9,I9,K9,M9) -> 0.76901278 | F9: =IF(G9>=$B$202,"A",IF(G9>=$B$203,"B",IF(G9>=$B$204,"C","D"))) -> A | G9: =SUM(N9:DL9)/$F$208 -> 0.78024432 | H9: =IF(I9>=$B$202,"A",IF(I9>=$B$203,"B",IF(I9>=$B$204,"C","D"))) -> A | I9: =SUM(DM9:FL9)/$H$208 -> 0.81229714 | J9: =IF(K9>=$B$202,"A",IF(K9>=$B$203,"B",IF(K9>=$B$204,"C","D"))) -> A | K9: =SUM(FM9:GR9)/$J$208 -> 0.7547609 | L9: =IF(M9>=$B$202,"A",IF(M9>=$B$203,"B",IF(M9>=$B$204,"C","D"))) -> B | M9: =SUM(GS9:JM9)/$L$208 -> 0.72874874 | N9: =VLOOKUP($B9,GTMI_Data!$B$2:$PK$595,N$211,FALSE)*N$215 -> 6 | O9: =IF(VLOOKUP($B9,GTMI_Data!$B$2:$PK$595,O$211,FALSE)=0,0,1) -> 1 | P9: =IF(VLOOKUP($B9,GTMI_Data!$B$2:$PK$595,P$211,FALSE)=0,0,1) -> 1 | Q9: =IF(VLOOKUP($B9,GTMI_Data!$B$2:$PK$595,Q$211,FALSE)=0,0,1) -> 1 | R9: =IF(VLOOKUP($B9,GTMI_Data!$B$2:$PK$595,R$211,FALSE)=0,0,1) -> 1 | S9: =VLOOKUP($B9,GTMI_Data!$B$2:$PK$595,S$211,FALSE)*S$215 -> 0 | T9: =IF(VLOOKUP($B9,GTMI_Data!$B$2:$PK$595,T$211,FALSE)=0,0,1) -> 0
A10: 2025 | B10: =VLOOKUP($C10,Economies!$C$2:$E$199,2,FALSE) -> AUS | C10: Australia | D10: =IF(E10>=$B$202,"A",IF(E10>=$B$203,"B",IF(E10>=$B$204,"C","D"))) -> A | E10: =AVERAGE(G10,I10,K10,M10) -> 0.98495271 | F10: =IF(G10>=$B$202,"A",IF(G10>=$B$203,"B",IF(G10>=$B$204,"C","D"))) -> A | G10: =SUM(N10:DL10)/$F$208 -> 0.98925743 | H10: =IF(I10>=$B$202,"A",IF(I10>=$B$203,"B",IF(I10>=$B$204,"C","D"))) -> A | I10: =SUM(DM10:FL10)/$H$208 -> 0.9923778 | J10: =IF(K10>=$B$202,"A",IF(K10>=$B$203,"B",IF(K10>=$B$204,"C","D"))) -> A | K10: =SUM(FM10:GR10)/$J$208 -> 0.9602406 | L10: =IF(M10>=$B$202,"A",IF(M10>=$B$203,"B",IF(M10>=$B$204,"C","D"))) -> A | M10: =SUM(GS10:JM10)/$L$208 -> 0.99793501 | N10: =VLOOKUP($B10,GTMI_Data!$B$2:$PK$595,N$211,FALSE)*N$215 -> 12 | O10: =IF(VLOOKUP($B10,GTMI_Data!$B$2:$PK$595,O$211,FALSE)=0,0,1) -> 1 | P10: =IF(VLOOKUP($B10,GTMI_Data!$B$2:$PK$595,P$211,FALSE)=0,0,1) -> 1 | Q10: =IF(VLOOKUP($B10,GTMI_Data!$B$2:$PK$595,Q$211,FALSE)=0,0,1) -> 1 | R10: =IF(VLOOKUP($B10,GTMI_Data!$B$2:$PK$595,R$211,FALSE)=0,0,1) -> 1 | S10: =VLOOKUP($B10,GTMI_Data!$B$2:$PK$595,S$211,FALSE)*S$215 -> 2 | T10: =IF(VLOOKUP($B10,GTMI_Data!$B$2:$PK$595,T$211,FALSE)=0,0,1) -> 1
A11: 2025 | B11: =VLOOKUP($C11,Economies!$C$2:$E$199,2,FALSE) -> AUT | C11: Austria | D11: =IF(E11>=$B$202,"A",IF(E11>=$B$203,"B",IF(E11>=$B$204,"C","D"))) -> A | E11: =AVERAGE(G11,I11,K11,M11) -> 0.92904049 | F11: =IF(G11>=$B$202,"A",IF(G11>=$B$203,"B",IF(G11>=$B$204,"C","D"))) -> A | G11: =SUM(N11:DL11)/$F$208 -> 0.95133411 | H11: =IF(I11>=$B$202,"A",IF(I11>=$B$203,"B",IF(I11>=$B$204,"C","D"))) -> A | I11: =SUM(DM11:FL11)/$H$208 -> 0.97599576 | J11: =IF(K11>=$B$202,"A",IF(K11>=$B$203,"B",IF(K11>=$B$204,"C","D"))) -> A | K11: =SUM(FM11:GR11)/$J$208 -> 0.85518195 | L11: =IF(M11>=$B$202,"A",IF(M11>=$B$203,"B",IF(M11>=$B$204,"C","D"))) -> A | M11: =SUM(GS11:JM11)/$L$208 -> 0.93365016 | N11: =VLOOKUP($B11,GTMI_Data!$B$2:$PK$595,N$211,FALSE)*N$215 -> 12 | O11: =IF(VLOOKUP($B11,GTMI_Data!$B$2:$PK$595,O$211,FALSE)=0,0,1) -> 1 | P11: =IF(VLOOKUP($B11,GTMI_Data!$B$2:$PK$595,P$211,FALSE)=0,0,1) -> 1 | Q11: =IF(VLOOKUP($B11,GTMI_Data!$B$2:$PK$595,Q$211,FALSE)=0,0,1) -> 1 | R11: =IF(VLOOKUP($B11,GTMI_Data!$B$2:$PK$595,R$211,FALSE)=0,0,1) -> 1 | S11: =VLOOKUP($B11,GTMI_Data!$B$2:$PK$595,S$211,FALSE)*S$215 -> 2 | T11: =IF(VLOOKUP($B11,GTMI_Data!$B$2:$PK$595,T$211,FALSE)=0,0,1) -> 1
A12: 2025 | B12: =VLOOKUP($C12,Economies!$C$2:$E$199,2,FALSE) -> AZE | C12: Azerbaijan | D12: =IF(E12>=$B$202,"A",IF(E12>=$B$203,"B",IF(E12>=$B$204,"C","D"))) -> A | E12: =AVERAGE(G12,I12,K12,M12) -> 0.76886315 | F12: =IF(G12>=$B$202,"A",IF(G12>=$B$203,"B",IF(G12>=$B$204,"C","D"))) -> A | G12: =SUM(N12:DL12)/$F$208 -> 0.92051485 | H12: =IF(I12>=$B$202,"A",IF(I12>=$B$203,"B",IF(I12>=$B$204,"C","D"))) -> A | I12: =SUM(DM12:FL12)/$H$208 -> 0.97439641 | J12: =IF(K12>=$B$202,"A",IF(K12>=$B$203,"B",IF(K12>=$B$204,"C","D"))) -> C | K12: =SUM(FM12:GR12)/$J$208 -> 0.38223158 | L12: =IF(M12>=$B$202,"A",IF(M12>=$B$203,"B",IF(M12>=$B$204,"C","D"))) -> A | M12: =SUM(GS12:JM12)/$L$208 -> 0.79830975 | N12: =VLOOKUP($B12,GTMI_Data!$B$2:$PK$595,N$211,FALSE)*N$215 -> 12 | O12: =IF(VLOOKUP($B12,GTMI_Data!$B$2:$PK$595,O$211,FALSE)=0,0,1) -> 1 | P12: =IF(VLOOKUP($B12,GTMI_Data!$B$2:$PK$595,P$211,FALSE)=0,0,1) -> 1 | Q12: =IF(VLOOKUP($B12,GTMI_Data!$B$2:$PK$595,Q$211,FALSE)=0,0,1) -> 1 | R12: =IF(VLOOKUP($B12,GTMI_Data!$B$2:$PK$595,R$211,FALSE)=0,0,1) -> 1 | S12: =VLOOKUP($B12,GTMI_Data!$B$2:$PK$595,S$211,FALSE)*S$215 -> 2 | T12: =IF(VLOOKUP($B12,GTMI_Data!$B$2:$PK$595,T$211,FALSE)=0,0,1) -> 1
A13: 2025 | B13: =VLOOKUP($C13,Economies!$C$2:$E$199,2,FALSE) -> BHS | C13: Bahamas | D13: =IF(E13>=$B$202,"A",IF(E13>=$B$203,"B",IF(E13>=$B$204,"C","D"))) -> B | E13: =AVERAGE(G13,I13,K13,M13) -> 0.50225716 | F13: =IF(G13>=$B$202,"A",IF(G13>=$B$203,"B",IF(G13>=$B$204,"C","D"))) -> B | G13: =SUM(N13:DL13)/$F$208 -> 0.57212714 | H13: =IF(I13>=$B$202,"A",IF(I13>=$B$203,"B",IF(I13>=$B$204,"C","D"))) -> B | I13: =SUM(DM13:FL13)/$H$208 -> 0.73046955 | J13: =IF(K13>=$B$202,"A",IF(K13>=$B$203,"B",IF(K13>=$B$204,"C","D"))) -> D | K13: =SUM(FM13:GR13)/$J$208 -> 0.16212331 | L13: =IF(M13>=$B$202,"A",IF(M13>=$B$203,"B",IF(M13>=$B$204,"C","D"))) -> B | M13: =SUM(GS13:JM13)/$L$208 -> 0.54430865 | N13: =VLOOKUP($B13,GTMI_Data!$B$2:$PK$595,N$211,FALSE)*N$215 -> 12 | O13: =IF(VLOOKUP($B13,GTMI_Data!$B$2:$PK$595,O$211,FALSE)=0,0,1) -> 1 | P13: =IF(VLOOKUP($B13,GTMI_Data!$B$2:$PK$595,P$211,FALSE)=0,0,1) -> 1 | Q13: =IF(VLOOKUP($B13,GTMI_Data!$B$2:$PK$595,Q$211,FALSE)=0,0,1) -> 1 | R13: =IF(VLOOKUP($B13,GTMI_Data!$B$2:$PK$595,R$211,FALSE)=0,0,1) -> 1 | S13: =VLOOKUP($B13,GTMI_Data!$B$2:$PK$595,S$211,FALSE)*S$215 -> 0 | T13: =IF(VLOOKUP($B13,GTMI_Data!$B$2:$PK$595,T$211,FALSE)=0,0,1) -> 0
... A30: 2025 | B30: =VLOOKUP($C30,Economies!$C$2:$E$199,2,FALSE) -> CPV | C30: Cabo Verde | D30: =IF(E30>=$B$202,"A",IF(E30>=$B$203,"B",IF(E30>=$B$204,"C","D"))) -> A | E30: =AVERAGE(G30,I30,K30,M30) -> 0.77412928 | F30: =IF(G30>=$B$202,"A",IF(G30>=$B$203,"B",IF(G30>=$B$204,"C","D"))) -> A | G30: =SUM(N30:DL30)/$F$208 -> 0.8022961 | H30: =IF(I30>=$B$202,"A",IF(I30>=$B$203,"B",IF(I30>=$B$204,"C","D"))) -> A | I30: =SUM(DM30:FL30)/$H$208 -> 0.83077584 | J30: =IF(K30>=$B$202,"A",IF(K30>=$B$203,"B",IF(K30>=$B$204,"C","D"))) -> B | K30: =SUM(FM30:GR30)/$J$208 -> 0.73796692 | L30: =IF(M30>=$B$202,"A",IF(M30>=$B$203,"B",IF(M30>=$B$204,"C","D"))) -> B | M30: =SUM(GS30:JM30)/$L$208 -> 0.72547826 | N30: =VLOOKUP($B30,GTMI_Data!$B$2:$PK$595,N$211,FALSE)*N$215 -> 12 | O30: =IF(VLOOKUP($B30,GTMI_Data!$B$2:$PK$595,O$211,FALSE)=0,0,1) -> 1 | P30: =IF(VLOOKUP($B30,GTMI_Data!$B$2:$PK$595,P$211,FALSE)=0,0,1) -> 1 | Q30: =IF(VLOOKUP($B30,GTMI_Data!$B$2:$PK$595,Q$211,FALSE)=0,0,1) -> 1 | R30: =IF(VLOOKUP($B30,GTMI_Data!$B$2:$PK$595,R$211,FALSE)=0,0,1) -> 1 | S30: =VLOOKUP($B30,GTMI_Data!$B$2:$PK$595,S$211,FALSE)*S$215 -> 0 | T30: =IF(VLOOKUP($B30,GTMI_Data!$B$2:$PK$595,T$211,FALSE)=0,0,1) -> 0

Sheet Stats
A1: WBreg | B1: Code | C1: Economy | D1: 2025 Grp | E1: GTMI | F1: CGSI | G1: CGSIs | H1: PSDI | I1: PSDIs | J1: DCEI | K1: DCEIs | L1: GTEI | M1: GTEIs | N1: Src | O1: Reg | P1: Level | Q1: FCS | R1: Borr | S1: Pop | T1: Sml
A2: MNA | B2: AFG | C2: Afghanistan | D2: =IF($AF$14="2025",VLOOKUP($B2,GTMI_Groups!$B$2:$M$199,3,FALSE),IF($AF$14="2022",VLOOKUP((" "&$B2&" "),GTMI_Data!$B$2:$QN$595,446,FALSE),IF($AF$14="2020",VLOOKUP((" "&$B2&" "),GTMI_Data!$B$2:$QN$595,446,FALSE),"-"))) -> D | E2: =IF($AF$14="2025",VLOOKUP($B2,GTMI_Groups!$B$2:$M$199,4,FALSE),IF($AF$14="2022",VLOOKUP((" "&$B2&" "),GTMI_Data!$B$2:$QN$595,447,FALSE),IF($AF$14="2020",VLOOKUP((" "&$B2&" "),GTMI_Data!$B$2:$QN$595,447,FALSE),"-"))) -> 0.12100789 | F2: =IF($AF$14="2025",VLOOKUP($B2,GTMI_Groups!$B$2:$M$199,5,FALSE),IF($AF$14="2022",VLOOKUP((" "&$B2&" "),GTMI_Data!$B$2:$QN$595,448,FALSE),IF($AF$14="2020",VLOOKUP((" "&$B2&" "),GTMI_Data!$B$2:$QN$595,448,FALSE),"-"))) -> D | G2: =IF($AF$14="2025",VLOOKUP($B2,GTMI_Groups!$B$2:$M$199,6,FALSE),IF($AF$14="2022",VLOOKUP((" "&$B2&" "),GTMI_Data!$B$2:$QN$595,449,FALSE),IF($AF$14="2020",VLOOKUP((" "&$B2&" "),GTMI_Data!$B$2:$QN$595,449,FALSE),"-"))) -> 0.16431801 | H2: =IF($AF$14="2025",VLOOKUP($B2,GTMI_Groups!$B$2:$M$199,7,FALSE),IF($AF$14="2022",VLOOKUP((" "&$B2&" "),GTMI_Data!$B$2:$QN$595,450,FALSE),IF($AF$14="2020",VLOOKUP((" "&$B2&" "),GTMI_Data!$B$2:$QN$595,450,FALSE),"-"))) -> C | I2: =IF($AF$14="2025",VLOOKUP($B2,GTMI_Groups!$B$2:$M$199,8,FALSE),IF($AF$14="2022",VLOOKUP((" "&$B2&" "),GTMI_Data!$B$2:$QN$595,451,FALSE),IF($AF$14="2020",VLOOKUP((" "&$B2&" "),GTMI_Data!$B$2:$QN$595,451,FALSE),"-"))) -> 0.27531004 | J2: =IF($AF$14="2025",VLOOKUP($B2,GTMI_Groups!$B$2:$M$199,9,FALSE),IF($AF$14="2022",VLOOKUP((" "&$B2&" "),GTMI_Data!$B$2:$QN$595,452,FALSE),IF($AF$14="2020",VLOOKUP((" "&$B2&" "),GTMI_Data!$B$2:$QN$595,452,FALSE),"-"))) -> D | K2: =IF($AF$14="2025",VLOOKUP($B2,GTMI_Groups!$B$2:$M$199,10,FALSE),IF($AF$14="2022",VLOOKUP((" "&$B2&" "),GTMI_Data!$B$2:$QN$595,453,FALSE),IF($AF$14="2020",VLOOKUP((" "&$B2&" "),GTMI_Data!$B$2:$QN$595,453,FALSE),"-"))) -> 0.019777444 | L2: =IF($AF$14="2025",VLOOKUP($B2,GTMI_Groups!$B$2:$M$199,11,FALSE),IF($AF$14="2022",VLOOKUP((" "&$B2&" "),GTMI_Data!$B$2:$QN$595,454,FALSE),IF($AF$14="2020",VLOOKUP((" "&$B2&" "),GTMI_Data!$B$2:$QN$595,454,FALSE),"-"))) -> D | M2: =IF($AF$14="2025",VLOOKUP($B2,GTMI_Groups!$B$2:$M$199,12,FALSE),IF($AF$14="2022",VLOOKUP((" "&$B2&" "),GTMI_Data!$B$2:$QN$595,455,FALSE),IF($AF$14="2020",VLOOKUP((" "&$B2&" "),GTMI_Data!$B$2:$QN$595,455,FALSE),"-"))) -> 0.024626087 | N2: =IF($AF$14="2025",VLOOKUP($B2,GTMI_Data!$B$2:$PR$595,427,FALSE),IF($AF$14="2022",VLOOKUP((" "&$B2&" "),GTMI_Data!$B$2:$QN$595,427,FALSE),IF($AF$14="2020",VLOOKUP((" "&$B2&" "),GTMI_Data!$B$2:$QN$595,427,FALSE),"-"))) -> R | O2: =IF($AF$14="2025",VLOOKUP($B2,GTMI_Data!$B$2:$PR$595,428,FALSE),IF($AF$14="2022",VLOOKUP((" "&$B2&" "),GTMI_Data!$B$2:$QN$595,428,FALSE),IF($AF$14="2020",VLOOKUP((" "&$B2&" "),GTMI_Data!$B$2:$QN$595,428,FALSE),"-"))) -> MNA | P2: =IF($AF$14="2025",VLOOKUP($B2,GTMI_Data!$B$2:$PR$595,429,FALSE),IF($AF$14="2022",VLOOKUP((" "&$B2&" "),GTMI_Data!$B$2:$QN$595,429,FALSE),IF($AF$14="2020",VLOOKUP((" "&$B2&" "),GTMI_Data!$B$2:$QN$595,429,FALSE),"-"))) -> L | Q2: =IF($AF$14="2025",VLOOKUP($B2,GTMI_Data!$B$2:$PR$595,430,FALSE),IF($AF$14="2022",VLOOKUP((" "&$B2&" "),GTMI_Data!$B$2:$QN$595,430,FALSE),IF($AF$14="2020",VLOOKUP((" "&$B2&" "),GTMI_Data!$B$2:$QN$595,430,FALSE),"-"))) -> FCS-1 | R2: =IF($AF$14="2025",VLOOKUP($B2,GTMI_Data!$B$2:$PR$595,431,FALSE),IF($AF$14="2022",VLOOKUP((" "&$B2&" "),GTMI_Data!$B$2:$QN$595,431,FALSE),IF($AF$14="2020",VLOOKUP((" "&$B2&" "),GTMI_Data!$B$2:$QN$595,431,FALSE),"-"))) -> IDA | S2: =IF($AF$14="2025",VLOOKUP($B2,GTMI_Data!$B$2:$PR$595,432,FALSE),IF($AF$14="2022",VLOOKUP((" "&$B2&" "),GTMI_Data!$B$2:$QN$595,432,FALSE),IF($AF$14="2020",VLOOKUP((" "&$B2&" "),GTMI_Data!$B$2:$QN$595,432,FALSE),"-")))/1000 -> 41.454761 | T2: =IF($AF$14="2025",VLOOKUP($B2,GTMI_Data!$B$2:$PR$595,433,FALSE),IF($AF$14="2022",VLOOKUP((" "&$B2&" "),GTMI_Data!$B$2:$QN$595,433,FALSE),IF($AF$14="2020",VLOOKUP((" "&$B2&" "),GTMI_Data!$B$2:$QN$595,433,FALSE),"-"))) -> 0
A3: ECA | B3: ALB | C3: Albania | D3: =IF($AF$14="2025",VLOOKUP($B3,GTMI_Groups!$B$2:$M$199,3,FALSE),IF($AF$14="2022",VLOOKUP((" "&$B3&" "),GTMI_Data!$B$2:$QN$595,446,FALSE),IF($AF$14="2020",VLOOKUP((" "&$B3&" "),GTMI_Data!$B$2:$QN$595,446,FALSE),"-"))) -> A | E3: =IF($AF$14="2025",VLOOKUP($B3,GTMI_Groups!$B$2:$M$199,4,FALSE),IF($AF$14="2022",VLOOKUP((" "&$B3&" "),GTMI_Data!$B$2:$QN$595,447,FALSE),IF($AF$14="2020",VLOOKUP((" "&$B3&" "),GTMI_Data!$B$2:$QN$595,447,FALSE),"-"))) -> 0.93852735 | F3: =IF($AF$14="2025",VLOOKUP($B3,GTMI_Groups!$B$2:$M$199,5,FALSE),IF($AF$14="2022",VLOOKUP((" "&$B3&" "),GTMI_Data!$B$2:$QN$595,448,FALSE),IF($AF$14="2020",VLOOKUP((" "&$B3&" "),GTMI_Data!$B$2:$QN$595,448,FALSE),"-"))) -> A | G3: =IF($AF$14="2025",VLOOKUP($B3,GTMI_Groups!$B$2:$M$199,6,FALSE),IF($AF$14="2022",VLOOKUP((" "&$B3&" "),GTMI_Data!$B$2:$QN$595,449,FALSE),IF($AF$14="2020",VLOOKUP((" "&$B3&" "),GTMI_Data!$B$2:$QN$595,449,FALSE),"-"))) -> 0.9307039 | H3: =IF($AF$14="2025",VLOOKUP($B3,GTMI_Groups!$B$2:$M$199,7,FALSE),IF($AF$14="2022",VLOOKUP((" "&$B3&" "),GTMI_Data!$B$2:$QN$595,450,FALSE),IF($AF$14="2020",VLOOKUP((" "&$B3&" "),GTMI_Data!$B$2:$QN$595,450,FALSE),"-"))) -> A | I3: =IF($AF$14="2025",VLOOKUP($B3,GTMI_Groups!$B$2:$M$199,8,FALSE),IF($AF$14="2022",VLOOKUP((" "&$B3&" "),GTMI_Data!$B$2:$QN$595,451,FALSE),IF($AF$14="2020",VLOOKUP((" "&$B3&" "),GTMI_Data!$B$2:$QN$595,451,FALSE),"-"))) -> 0.94100343 | J3: =IF($AF$14="2025",VLOOKUP($B3,GTMI_Groups!$B$2:$M$199,9,FALSE),IF($AF$14="2022",VLOOKUP((" "&$B3&" "),GTMI_Data!$B$2:$QN$595,452,FALSE),IF($AF$14="2020",VLOOKUP((" "&$B3&" "),GTMI_Data!$B$2:$QN$595,452,FALSE),"-"))) -> A | K3: =IF($AF$14="2025",VLOOKUP($B3,GTMI_Groups!$B$2:$M$199,10,FALSE),IF($AF$14="2022",VLOOKUP((" "&$B3&" "),GTMI_Data!$B$2:$QN$595,453,FALSE),IF($AF$14="2020",VLOOKUP((" "&$B3&" "),GTMI_Data!$B$2:$QN$595,453,FALSE),"-"))) -> 0.95055639 | L3: =IF($AF$14="2025",VLOOKUP($B3,GTMI_Groups!$B$2:$M$199,11,FALSE),IF($AF$14="2022",VLOOKUP((" "&$B3&" "),GTMI_Data!$B$2:$QN$595,454,FALSE),IF($AF$14="2020",VLOOKUP((" "&$B3&" "),GTMI_Data!$B$2:$QN$595,454,FALSE),"-"))) -> A | M3: =IF($AF$14="2025",VLOOKUP($B3,GTMI_Groups!$B$2:$M$199,12,FALSE),IF($AF$14="2022",VLOOKUP((" "&$B3&" "),GTMI_Data!$B$2:$QN$595,455,FALSE),IF($AF$14="2020",VLOOKUP((" "&$B3&" "),GTMI_Data!$B$2:$QN$595,455,FALSE),"-"))) -> 0.93184568 | N3: =IF($AF$14="2025",VLOOKUP($B3,GTMI_Data!$B$2:$PR$595,427,FALSE),IF($AF$14="2022",VLOOKUP((" "&$B3&" "),GTMI_Data!$B$2:$QN$595,427,FALSE),IF($AF$14="2020",VLOOKUP((" "&$B3&" "),GTMI_Data!$B$2:$QN$595,427,FALSE),"-"))) -> S | O3: =IF($AF$14="2025",VLOOKUP($B3,GTMI_Data!$B$2:$PR$595,428,FALSE),IF($AF$14="2022",VLOOKUP((" "&$B3&" "),GTMI_Data!$B$2:$QN$595,428,FALSE),IF($AF$14="2020",VLOOKUP((" "&$B3&" "),GTMI_Data!$B$2:$QN$595,428,FALSE),"-"))) -> ECA | P3: =IF($AF$14="2025",VLOOKUP($B3,GTMI_Data!$B$2:$PR$595,429,FALSE),IF($AF$14="2022",VLOOKUP((" "&$B3&" "),GTMI_Data!$B$2:$QN$595,429,FALSE),IF($AF$14="2020",VLOOKUP((" "&$B3&" "),GTMI_Data!$B$2:$QN$595,429,FALSE),"-"))) -> UM | Q3: =IF($AF$14="2025",VLOOKUP($B3,GTMI_Data!$B$2:$PR$595,430,FALSE),IF($AF$14="2022",VLOOKUP((" "&$B3&" "),GTMI_Data!$B$2:$QN$595,430,FALSE),IF($AF$14="2020",VLOOKUP((" "&$B3&" "),GTMI_Data!$B$2:$QN$595,430,FALSE),"-"))) -> - | R3: =IF($AF$14="2025",VLOOKUP($B3,GTMI_Data!$B$2:$PR$595,431,FALSE),IF($AF$14="2022",VLOOKUP((" "&$B3&" "),GTMI_Data!$B$2:$QN$595,431,FALSE),IF($AF$14="2020",VLOOKUP((" "&$B3&" "),GTMI_Data!$B$2:$QN$595,431,FALSE),"-"))) -> IBRD | S3: =IF($AF$14="2025",VLOOKUP($B3,GTMI_Data!$B$2:$PR$595,432,FALSE),IF($AF$14="2022",VLOOKUP((" "&$B3&" "),GTMI_Data!$B$2:$QN$595,432,FALSE),IF($AF$14="2020",VLOOKUP((" "&$B3&" "),GTMI_Data!$B$2:$QN$595,432,FALSE),"-")))/1000 -> 2.811655 | T3: =IF($AF$14="2025",VLOOKUP($B3,GTMI_Data!$B$2:$PR$595,433,FALSE),IF($AF$14="2022",VLOOKUP((" "&$B3&" "),GTMI_Data!$B$2:$QN$595,433,FALSE),IF($AF$14="2020",VLOOKUP((" "&$B3&" "),GTMI_Data!$B$2:$QN$595,433,FALSE),"-"))) -> 0
A4: MNA | B4: DZA | C4: Algeria | D4: =IF($AF$14="2025",VLOOKUP($B4,GTMI_Groups!$B$2:$M$199,3,FALSE),IF($AF$14="2022",VLOOKUP((" "&$B4&" "),GTMI_Data!$B$2:$QN$595,446,FALSE),IF($AF$14="2020",VLOOKUP((" "&$B4&" "),GTMI_Data!$B$2:$QN$595,446,FALSE),"-"))) -> B | E4: =IF($AF$14="2025",VLOOKUP($B4,GTMI_Groups!$B$2:$M$199,4,FALSE),IF($AF$14="2022",VLOOKUP((" "&$B4&" "),GTMI_Data!$B$2:$QN$595,447,FALSE),IF($AF$14="2020",VLOOKUP((" "&$B4&" "),GTMI_Data!$B$2:$QN$595,447,FALSE),"-"))) -> 0.55487551 | F4: =IF($AF$14="2025",VLOOKUP($B4,GTMI_Groups!$B$2:$M$199,5,FALSE),IF($AF$14="2022",VLOOKUP((" "&$B4&" "),GTMI_Data!$B$2:$QN$595,448,FALSE),IF($AF$14="2020",VLOOKUP((" "&$B4&" "),GTMI_Data!$B$2:$QN$595,448,FALSE),"-"))) -> B | G4: =IF($AF$14="2025",VLOOKUP($B4,GTMI_Groups!$B$2:$M$199,6,FALSE),IF($AF$14="2022",VLOOKUP((" "&$B4&" "),GTMI_Data!$B$2:$QN$595,449,FALSE),IF($AF$14="2020",VLOOKUP((" "&$B4&" "),GTMI_Data!$B$2:$QN$595,449,FALSE),"-"))) -> 0.54462573 | H4: =IF($AF$14="2025",VLOOKUP($B4,GTMI_Groups!$B$2:$M$199,7,FALSE),IF($AF$14="2022",VLOOKUP((" "&$B4&" "),GTMI_Data!$B$2:$QN$595,450,FALSE),IF($AF$14="2020",VLOOKUP((" "&$B4&" "),GTMI_Data!$B$2:$QN$595,450,FALSE),"-"))) -> B | I4: =IF($AF$14="2025",VLOOKUP($B4,GTMI_Groups!$B$2:$M$199,8,FALSE),IF($AF$14="2022",VLOOKUP((" "&$B4&" "),GTMI_Data!$B$2:$QN$595,451,FALSE),IF($AF$14="2020",VLOOKUP((" "&$B4&" "),GTMI_Data!$B$2:$QN$595,451,FALSE),"-"))) -> 0.68150204 | J4: =IF($AF$14="2025",VLOOKUP($B4,GTMI_Groups!$B$2:$M$199,9,FALSE),IF($AF$14="2022",VLOOKUP((" "&$B4&" "),GTMI_Data!$B$2:$QN$595,452,FALSE),IF($AF$14="2020",VLOOKUP((" "&$B4&" "),GTMI_Data!$B$2:$QN$595,452,FALSE),"-"))) -> C | K4: =IF($AF$14="2025",VLOOKUP($B4,GTMI_Groups!$B$2:$M$199,10,FALSE),IF($AF$14="2022",VLOOKUP((" "&$B4&" "),GTMI_Data!$B$2:$QN$595,453,FALSE),IF($AF$14="2020",VLOOKUP((" "&$B4&" "),GTMI_Data!$B$2:$QN$595,453,FALSE),"-"))) -> 0.39334737 | L4: =IF($AF$14="2025",VLOOKUP($B4,GTMI_Groups!$B$2:$M$199,11,FALSE),IF($AF$14="2022",VLOOKUP((" "&$B4&" "),GTMI_Data!$B$2:$QN$595,454,FALSE),IF($AF$14="2020",VLOOKUP((" "&$B4&" "),GTMI_Data!$B$2:$QN$595,454,FALSE),"-"))) -> B | M4: =IF($AF$14="2025",VLOOKUP($B4,GTMI_Groups!$B$2:$M$199,12,FALSE),IF($AF$14="2022",VLOOKUP((" "&$B4&" "),GTMI_Data!$B$2:$QN$595,455,FALSE),IF($AF$14="2020",VLOOKUP((" "&$B4&" "),GTMI_Data!$B$2:$QN$595,455,FALSE),"-"))) -> 0.60002691 | N4: =IF($AF$14="2025",VLOOKUP($B4,GTMI_Data!$B$2:$PR$595,427,FALSE),IF($AF$14="2022",VLOOKUP((" "&$B4&" "),GTMI_Data!$B$2:$QN$595,427,FALSE),IF($AF$14="2020",VLOOKUP((" "&$B4&" "),GTMI_Data!$B$2:$QN$595,427,FALSE),"-"))) -> S | O4: =IF($AF$14="2025",VLOOKUP($B4,GTMI_Data!$B$2:$PR$595,428,FALSE),IF($AF$14="2022",VLOOKUP((" "&$B4&" "),GTMI_Data!$B$2:$QN$595,428,FALSE),IF($AF$14="2020",VLOOKUP((" "&$B4&" "),GTMI_Data!$B$2:$QN$595,428,FALSE),"-"))) -> MNA | P4: =IF($AF$14="2025",VLOOKUP($B4,GTMI_Data!$B$2:$PR$595,429,FALSE),IF($AF$14="2022",VLOOKUP((" "&$B4&" "),GTMI_Data!$B$2:$QN$595,429,FALSE),IF($AF$14="2020",VLOOKUP((" "&$B4&" "),GTMI_Data!$B$2:$QN$595,429,FALSE),"-"))) -> UM | Q4: =IF($AF$14="2025",VLOOKUP($B4,GTMI_Data!$B$2:$PR$595,430,FALSE),IF($AF$14="2022",VLOOKUP((" "&$B4&" "),GTMI_Data!$B$2:$QN$595,430,FALSE),IF($AF$14="2020",VLOOKUP((" "&$B4&" "),GTMI_Data!$B$2:$QN$595,430,FALSE),"-"))) -> - | R4: =IF($AF$14="2025",VLOOKUP($B4,GTMI_Data!$B$2:$PR$595,431,FALSE),IF($AF$14="2022",VLOOKUP((" "&$B4&" "),GTMI_Data!$B$2:$QN$595,431,FALSE),IF($AF$14="2020",VLOOKUP((" "&$B4&" "),GTMI_Data!$B$2:$QN$595,431,FALSE),"-"))) -> IBRD | S4: =IF($AF$14="2025",VLOOKUP($B4,GTMI_Data!$B$2:$PR$595,432,FALSE),IF($AF$14="2022",VLOOKUP((" "&$B4&" "),GTMI_Data!$B$2:$QN$595,432,FALSE),IF($AF$14="2020",VLOOKUP((" "&$B4&" "),GTMI_Data!$B$2:$QN$595,432,FALSE),"-")))/1000 -> 46.164219 | T4: =IF($AF$14="2025",VLOOKUP($B4,GTMI_Data!$B$2:$PR$595,433,FALSE),IF($AF$14="2022",VLOOKUP((" "&$B4&" "),GTMI_Data!$B$2:$QN$595,433,FALSE),IF($AF$14="2020",VLOOKUP((" "&$B4&" "),GTMI_Data!$B$2:$QN$595,433,FALSE),"-"))) -> 0
A5: - | B5: AND | C5: Andorra | D5: =IF($AF$14="2025",VLOOKUP($B5,GTMI_Groups!$B$2:$M$199,3,FALSE),IF($AF$14="2022",VLOOKUP((" "&$B5&" "),GTMI_Data!$B$2:$QN$595,446,FALSE),IF($AF$14="2020",VLOOKUP((" "&$B5&" "),GTMI_Data!$B$2:$QN$595,446,FALSE),"-"))) -> C | E5: =IF($AF$14="2025",VLOOKUP($B5,GTMI_Groups!$B$2:$M$199,4,FALSE),IF($AF$14="2022",VLOOKUP((" "&$B5&" "),GTMI_Data!$B$2:$QN$595,447,FALSE),IF($AF$14="2020",VLOOKUP((" "&$B5&" "),GTMI_Data!$B$2:$QN$595,447,FALSE),"-"))) -> 0.39016981 | F5: =IF($AF$14="2025",VLOOKUP($B5,GTMI_Groups!$B$2:$M$199,5,FALSE),IF($AF$14="2022",VLOOKUP((" "&$B5&" "),GTMI_Data!$B$2:$QN$595,448,FALSE),IF($AF$14="2020",VLOOKUP((" "&$B5&" "),GTMI_Data!$B$2:$QN$595,448,FALSE),"-"))) -> C | G5: =IF($AF$14="2025",VLOOKUP($B5,GTMI_Groups!$B$2:$M$199,6,FALSE),IF($AF$14="2022",VLOOKUP((" "&$B5&" "),GTMI_Data!$B$2:$QN$595,449,FALSE),IF($AF$14="2020",VLOOKUP((" "&$B5&" "),GTMI_Data!$B$2:$QN$595,449,FALSE),"-"))) -> 0.33226905 | H5: =IF($AF$14="2025",VLOOKUP($B5,GTMI_Groups!$B$2:$M$199,7,FALSE),IF($AF$14="2022",VLOOKUP((" "&$B5&" "),GTMI_Data!$B$2:$QN$595,450,FALSE),IF($AF$14="2020",VLOOKUP((" "&$B5&" "),GTMI_Data!$B$2:$QN$595,450,FALSE),"-"))) -> B | I5: =IF($AF$14="2025",VLOOKUP($B5,GTMI_Groups!$B$2:$M$199,8,FALSE),IF($AF$14="2022",VLOOKUP((" "&$B5&" "),GTMI_Data!$B$2:$QN$595,451,FALSE),IF($AF$14="2020",VLOOKUP((" "&$B5&" "),GTMI_Data!$B$2:$QN$595,451,FALSE),"-"))) -> 0.56111412 | J5: =IF($AF$14="2025",VLOOKUP($B5,GTMI_Groups!$B$2:$M$199,9,FALSE),IF($AF$14="2022",VLOOKUP((" "&$B5&" "),GTMI_Data!$B$2:$QN$595,452,FALSE),IF($AF$14="2020",VLOOKUP((" "&$B5&" "),GTMI_Data!$B$2:$QN$595,452,FALSE),"-"))) -> D | K5: =IF($AF$14="2025",VLOOKUP($B5,GTMI_Groups!$B$2:$M$199,10,FALSE),IF($AF$14="2022",VLOOKUP((" "&$B5&" "),GTMI_Data!$B$2:$QN$595,453,FALSE),IF($AF$14="2020",VLOOKUP((" "&$B5&" "),GTMI_Data!$B$2:$QN$595,453,FALSE),"-"))) -> 0.20413233 | L5: =IF($AF$14="2025",VLOOKUP($B5,GTMI_Groups!$B$2:$M$199,11,FALSE),IF($AF$14="2022",VLOOKUP((" "&$B5&" "),GTMI_Data!$B$2:$QN$595,454,FALSE),IF($AF$14="2020",VLOOKUP((" "&$B5&" "),GTMI_Data!$B$2:$QN$595,454,FALSE),"-"))) -> C | M5: =IF($AF$14="2025",VLOOKUP($B5,GTMI_Groups!$B$2:$M$199,12,FALSE),IF($AF$14="2022",VLOOKUP((" "&$B5&" "),GTMI_Data!$B$2:$QN$595,455,FALSE),IF($AF$14="2020",VLOOKUP((" "&$B5&" "),GTMI_Data!$B$2:$QN$595,455,FALSE),"-"))) -> 0.46316375 | N5: =IF($AF$14="2025",VLOOKUP($B5,GTMI_Data!$B$2:$PR$595,427,FALSE),IF($AF$14="2022",VLOOKUP((" "&$B5&" "),GTMI_Data!$B$2:$QN$595,427,FALSE),IF($AF$14="2020",VLOOKUP((" "&$B5&" "),GTMI_Data!$B$2:$QN$595,427,FALSE),"-"))) -> R | O5: =IF($AF$14="2025",VLOOKUP($B5,GTMI_Data!$B$2:$PR$595,428,FALSE),IF($AF$14="2022",VLOOKUP((" "&$B5&" "),GTMI_Data!$B$2:$QN$595,428,FALSE),IF($AF$14="2020",VLOOKUP((" "&$B5&" "),GTMI_Data!$B$2:$QN$595,428,FALSE),"-"))) -> ECA | P5: =IF($AF$14="2025",VLOOKUP($B5,GTMI_Data!$B$2:$PR$595,429,FALSE),IF($AF$14="2022",VLOOKUP((" "&$B5&" "),GTMI_Data!$B$2:$QN$595,429,FALSE),IF($AF$14="2020",VLOOKUP((" "&$B5&" "),GTMI_Data!$B$2:$QN$595,429,FALSE),"-"))) -> H | Q5: =IF($AF$14="2025",VLOOKUP($B5,GTMI_Data!$B$2:$PR$595,430,FALSE),IF($AF$14="2022",VLOOKUP((" "&$B5&" "),GTMI_Data!$B$2:$QN$595,430,FALSE),IF($AF$14="2020",VLOOKUP((" "&$B5&" "),GTMI_Data!$B$2:$QN$595,430,FALSE),"-"))) -> - | R5: =IF($AF$14="2025",VLOOKUP($B5,GTMI_Data!$B$2:$PR$595,431,FALSE),IF($AF$14="2022",VLOOKUP((" "&$B5&" "),GTMI_Data!$B$2:$QN$595,431,FALSE),IF($AF$14="2020",VLOOKUP((" "&$B5&" "),GTMI_Data!$B$2:$QN$595,431,FALSE),"-"))) -> - | S5: =IF($AF$14="2025",VLOOKUP($B5,GTMI_Data!$B$2:$PR$595,432,FALSE),IF($AF$14="2022",VLOOKUP((" "&$B5&" "),GTMI_Data!$B$2:$QN$595,432,FALSE),IF($AF$14="2020",VLOOKUP((" "&$B5&" "),GTMI_Data!$B$2:$QN$595,432,FALSE),"-")))/1000 -> 0.0809 | T5: =IF($AF$14="2025",VLOOKUP($B5,GTMI_Data!$B$2:$PR$595,433,FALSE),IF($AF$14="2022",VLOOKUP((" "&$B5&" "),GTMI_Data!$B$2:$QN$595,433,FALSE),IF($AF$14="2020",VLOOKUP((" "&$B5&" "),GTMI_Data!$B$2:$QN$595,433,FALSE),"-"))) -> 1
A6: AFE | B6: AGO | C6: Angola | D6: =IF($AF$14="2025",VLOOKUP($B6,GTMI_Groups!$B$2:$M$199,3,FALSE),IF($AF$14="2022",VLOOKUP((" "&$B6&" "),GTMI_Data!$B$2:$QN$595,446,FALSE),IF($AF$14="2020",VLOOKUP((" "&$B6&" "),GTMI_Data!$B$2:$QN$595,446,FALSE),"-"))) -> B | E6: =IF($AF$14="2025",VLOOKUP($B6,GTMI_Groups!$B$2:$M$199,4,FALSE),IF($AF$14="2022",VLOOKUP((" "&$B6&" "),GTMI_Data!$B$2:$QN$595,447,FALSE),IF($AF$14="2020",VLOOKUP((" "&$B6&" "),GTMI_Data!$B$2:$QN$595,447,FALSE),"-"))) -> 0.59293688 | F6: =IF($AF$14="2025",VLOOKUP($B6,GTMI_Groups!$B$2:$M$199,5,FALSE),IF($AF$14="2022",VLOOKUP((" "&$B6&" "),GTMI_Data!$B$2:$QN$595,448,FALSE),IF($AF$14="2020",VLOOKUP((" "&$B6&" "),GTMI_Data!$B$2:$QN$595,448,FALSE),"-"))) -> B | G6: =IF($AF$14="2025",VLOOKUP($B6,GTMI_Groups!$B$2:$M$199,6,FALSE),IF($AF$14="2022",VLOOKUP((" "&$B6&" "),GTMI_Data!$B$2:$QN$595,449,FALSE),IF($AF$14="2020",VLOOKUP((" "&$B6&" "),GTMI_Data!$B$2:$QN$595,449,FALSE),"-"))) -> 0.69489029 | H6: =IF($AF$14="2025",VLOOKUP($B6,GTMI_Groups!$B$2:$M$199,7,FALSE),IF($AF$14="2022",VLOOKUP((" "&$B6&" "),GTMI_Data!$B$2:$QN$595,450,FALSE),IF($AF$14="2020",VLOOKUP((" "&$B6&" "),GTMI_Data!$B$2:$QN$595,450,FALSE),"-"))) -> A | I6: =IF($AF$14="2025",VLOOKUP($B6,GTMI_Groups!$B$2:$M$199,8,FALSE),IF($AF$14="2022",VLOOKUP((" "&$B6&" "),GTMI_Data!$B$2:$QN$595,451,FALSE),IF($AF$14="2020",VLOOKUP((" "&$B6&" "),GTMI_Data!$B$2:$QN$595,451,FALSE),"-"))) -> 0.76534596 | J6: =IF($AF$14="2025",VLOOKUP($B6,GTMI_Groups!$B$2:$M$199,9,FALSE),IF($AF$14="2022",VLOOKUP((" "&$B6&" "),GTMI_Data!$B$2:$QN$595,452,FALSE),IF($AF$14="2020",VLOOKUP((" "&$B6&" "),GTMI_Data!$B$2:$QN$595,452,FALSE),"-"))) -> C | K6: =IF($AF$14="2025",VLOOKUP($B6,GTMI_Groups!$B$2:$M$199,10,FALSE),IF($AF$14="2022",VLOOKUP((" "&$B6&" "),GTMI_Data!$B$2:$QN$595,453,FALSE),IF($AF$14="2020",VLOOKUP((" "&$B6&" "),GTMI_Data!$B$2:$QN$595,453,FALSE),"-"))) -> 0.33278797 | L6: =IF($AF$14="2025",VLOOKUP($B6,GTMI_Groups!$B$2:$M$199,11,FALSE),IF($AF$14="2022",VLOOKUP((" "&$B6&" "),GTMI_Data!$B$2:$QN$595,454,FALSE),IF($AF$14="2020",VLOOKUP((" "&$B6&" "),GTMI_Data!$B$2:$QN$595,454,FALSE),"-"))) -> B | M6: =IF($AF$14="2025",VLOOKUP($B6,GTMI_Groups!$B$2:$M$199,12,FALSE),IF($AF$14="2022",VLOOKUP((" "&$B6&" "),GTMI_Data!$B$2:$QN$595,455,FALSE),IF($AF$14="2020",VLOOKUP((" "&$B6&" "),GTMI_Data!$B$2:$QN$595,455,FALSE),"-"))) -> 0.5787233 | N6: =IF($AF$14="2025",VLOOKUP($B6,GTMI_Data!$B$2:$PR$595,427,FALSE),IF($AF$14="2022",VLOOKUP((" "&$B6&" "),GTMI_Data!$B$2:$QN$595,427,FALSE),IF($AF$14="2020",VLOOKUP((" "&$B6&" "),GTMI_Data!$B$2:$QN$595,427,FALSE),"-"))) -> S | O6: =IF($AF$14="2025",VLOOKUP($B6,GTMI_Data!$B$2:$PR$595,428,FALSE),IF($AF$14="2022",VLOOKUP((" "&$B6&" "),GTMI_Data!$B$2:$QN$595,428,FALSE),IF($AF$14="2020",VLOOKUP((" "&$B6&" "),GTMI_Data!$B$2:$QN$595,428,FALSE),"-"))) -> AFR | P6: =IF($AF$14="2025",VLOOKUP($B6,GTMI_Data!$B$2:$PR$595,429,FALSE),IF($AF$14="2022",VLOOKUP((" "&$B6&" "),GTMI_Data!$B$2:$QN$595,429,FALSE),IF($AF$14="2020",VLOOKUP((" "&$B6&" "),GTMI_Data!$B$2:$QN$595,429,FALSE),"-"))) -> LM | Q6: =IF($AF$14="2025",VLOOKUP($B6,GTMI_Data!$B$2:$PR$595,430,FALSE),IF($AF$14="2022",VLOOKUP((" "&$B6&" "),GTMI_Data!$B$2:$QN$595,430,FALSE),IF($AF$14="2020",VLOOKUP((" "&$B6&" "),GTMI_Data!$B$2:$QN$595,430,FALSE),"-"))) -> - | R6: =IF($AF$14="2025",VLOOKUP($B6,GTMI_Data!$B$2:$PR$595,431,FALSE),IF($AF$14="2022",VLOOKUP((" "&$B6&" "),GTMI_Data!$B$2:$QN$595,431,FALSE),IF($AF$14="2020",VLOOKUP((" "&$B6&" "),GTMI_Data!$B$2:$QN$595,431,FALSE),"-"))) -> IBRD | S6: =IF($AF$14="2025",VLOOKUP($B6,GTMI_Data!$B$2:$PR$595,432,FALSE),IF($AF$14="2022",VLOOKUP((" "&$B6&" "),GTMI_Data!$B$2:$QN$595,432,FALSE),IF($AF$14="2020",VLOOKUP((" "&$B6&" "),GTMI_Data!$B$2:$QN$595,432,FALSE),"-")))/1000 -> 36.749906 | T6: =IF($AF$14="2025",VLOOKUP($B6,GTMI_Data!$B$2:$PR$595,433,FALSE),IF($AF$14="2022",VLOOKUP((" "&$B6&" "),GTMI_Data!$B$2:$QN$595,433,FALSE),IF($AF$14="2020",VLOOKUP((" "&$B6&" "),GTMI_Data!$B$2:$QN$595,433,FALSE),"-"))) -> 0
A7: LCR | B7: ATG | C7: Antigua and Barbuda | D7: =IF($AF$14="2025",VLOOKUP($B7,GTMI_Groups!$B$2:$M$199,3,FALSE),IF($AF$14="2022",VLOOKUP((" "&$B7&" "),GTMI_Data!$B$2:$QN$595,446,FALSE),IF($AF$14="2020",VLOOKUP((" "&$B7&" "),GTMI_Data!$B$2:$QN$595,446,FALSE),"-"))) -> D | E7: =IF($AF$14="2025",VLOOKUP($B7,GTMI_Groups!$B$2:$M$199,4,FALSE),IF($AF$14="2022",VLOOKUP((" "&$B7&" "),GTMI_Data!$B$2:$QN$595,447,FALSE),IF($AF$14="2020",VLOOKUP((" "&$B7&" "),GTMI_Data!$B$2:$QN$595,447,FALSE),"-"))) -> 0.19382978 | F7: =IF($AF$14="2025",VLOOKUP($B7,GTMI_Groups!$B$2:$M$199,5,FALSE),IF($AF$14="2022",VLOOKUP((" "&$B7&" "),GTMI_Data!$B$2:$QN$595,448,FALSE),IF($AF$14="2020",VLOOKUP((" "&$B7&" "),GTMI_Data!$B$2:$QN$595,448,FALSE),"-"))) -> C | G7: =IF($AF$14="2025",VLOOKUP($B7,GTMI_Groups!$B$2:$M$199,6,FALSE),IF($AF$14="2022",VLOOKUP((" "&$B7&" "),GTMI_Data!$B$2:$QN$595,449,FALSE),IF($AF$14="2020",VLOOKUP((" "&$B7&" "),GTMI_Data!$B$2:$QN$595,449,FALSE),"-"))) -> 0.35490091 | H7: =IF($AF$14="2025",VLOOKUP($B7,GTMI_Groups!$B$2:$M$199,7,FALSE),IF($AF$14="2022",VLOOKUP((" "&$B7&" "),GTMI_Data!$B$2:$QN$595,450,FALSE),IF($AF$14="2020",VLOOKUP((" "&$B7&" "),GTMI_Data!$B$2:$QN$595,450,FALSE),"-"))) -> D | I7: =IF($AF$14="2025",VLOOKUP($B7,GTMI_Groups!$B$2:$M$199,8,FALSE),IF($AF$14="2022",VLOOKUP((" "&$B7&" "),GTMI_Data!$B$2:$QN$595,451,FALSE),IF($AF$14="2020",VLOOKUP((" "&$B7&" "),GTMI_Data!$B$2:$QN$595,451,FALSE),"-"))) -> 0.16733845 | J7: =IF($AF$14="2025",VLOOKUP($B7,GTMI_Groups!$B$2:$M$199,9,FALSE),IF($AF$14="2022",VLOOKUP((" "&$B7&" "),GTMI_Data!$B$2:$QN$595,452,FALSE),IF($AF$14="2020",VLOOKUP((" "&$B7&" "),GTMI_Data!$B$2:$QN$595,452,FALSE),"-"))) -> D | K7: =IF($AF$14="2025",VLOOKUP($B7,GTMI_Groups!$B$2:$M$199,10,FALSE),IF($AF$14="2022",VLOOKUP((" "&$B7&" "),GTMI_Data!$B$2:$QN$595,453,FALSE),IF($AF$14="2020",VLOOKUP((" "&$B7&" "),GTMI_Data!$B$2:$QN$595,453,FALSE),"-"))) -> 0.061804511 | L7: =IF($AF$14="2025",VLOOKUP($B7,GTMI_Groups!$B$2:$M$199,11,FALSE),IF($AF$14="2022",VLOOKUP((" "&$B7&" "),GTMI_Data!$B$2:$QN$595,454,FALSE),IF($AF$14="2020",VLOOKUP((" "&$B7&" "),GTMI_Data!$B$2:$QN$595,454,FALSE),"-"))) -> D | M7: =IF($AF$14="2025",VLOOKUP($B7,GTMI_Groups!$B$2:$M$199,12,FALSE),IF($AF$14="2022",VLOOKUP((" "&$B7&" "),GTMI_Data!$B$2:$QN$595,455,FALSE),IF($AF$14="2020",VLOOKUP((" "&$B7&" "),GTMI_Data!$B$2:$QN$595,455,FALSE),"-"))) -> 0.19127524 | N7: =IF($AF$14="2025",VLOOKUP($B7,GTMI_Data!$B$2:$PR$595,427,FALSE),IF($AF$14="2022",VLOOKUP((" "&$B7&" "),GTMI_Data!$B$2:$QN$595,427,FALSE),IF($AF$14="2020",VLOOKUP((" "&$B7&" "),GTMI_Data!$B$2:$QN$595,427,FALSE),"-"))) -> R | O7: =IF($AF$14="2025",VLOOKUP($B7,GTMI_Data!$B$2:$PR$595,428,FALSE),IF($AF$14="2022",VLOOKUP((" "&$B7&" "),GTMI_Data!$B$2:$QN$595,428,FALSE),IF($AF$14="2020",VLOOKUP((" "&$B7&" "),GTMI_Data!$B$2:$QN$595,428,FALSE),"-"))) -> LCR | P7: =IF($AF$14="2025",VLOOKUP($B7,GTMI_Data!$B$2:$PR$595,429,FALSE),IF($AF$14="2022",VLOOKUP((" "&$B7&" "),GTMI_Data!$B$2:$QN$595,429,FALSE),IF($AF$14="2020",VLOOKUP((" "&$B7&" "),GTMI_Data!$B$2:$QN$595,429,FALSE),"-"))) -> H | Q7: =IF($AF$14="2025",VLOOKUP($B7,GTMI_Data!$B$2:$PR$595,430,FALSE),IF($AF$14="2022",VLOOKUP((" "&$B7&" "),GTMI_Data!$B$2:$QN$595,430,FALSE),IF($AF$14="2020",VLOOKUP((" "&$B7&" "),GTMI_Data!$B$2:$QN$595,430,FALSE),"-"))) -> - | R7: =IF($AF$14="2025",VLOOKUP($B7,GTMI_Data!$B$2:$PR$595,431,FALSE),IF($AF$14="2022",VLOOKUP((" "&$B7&" "),GTMI_Data!$B$2:$QN$595,431,FALSE),IF($AF$14="2020",VLOOKUP((" "&$B7&" "),GTMI_Data!$B$2:$QN$595,431,FALSE),"-"))) -> IBRD | S7: =IF($AF$14="2025",VLOOKUP($B7,GTMI_Data!$B$2:$PR$595,432,FALSE),IF($AF$14="2022",VLOOKUP((" "&$B7&" "),GTMI_Data!$B$2:$QN$595,432,FALSE),IF($AF$14="2020",VLOOKUP((" "&$B7&" "),GTMI_Data!$B$2:$QN$595,432,FALSE),"-")))/1000 -> 0.0933 | T7: =IF($AF$14="2025",VLOOKUP($B7,GTMI_Data!$B$2:$PR$595,433,FALSE),IF($AF$14="2022",VLOOKUP((" "&$B7&" "),GTMI_Data!$B$2:$QN$595,433,FALSE),IF($AF$14="2020",VLOOKUP((" "&$B7&" "),GTMI_Data!$B$2:$QN$595,433,FALSE),"-"))) -> 1
A8: LCR | B8: ARG | C8: Argentina | D8: =IF($AF$14="2025",VLOOKUP($B8,GTMI_Groups!$B$2:$M$199,3,FALSE),IF($AF$14="2022",VLOOKUP((" "&$B8&" "),GTMI_Data!$B$2:$QN$595,446,FALSE),IF($AF$14="2020",VLOOKUP((" "&$B8&" "),GTMI_Data!$B$2:$QN$595,446,FALSE),"-"))) -> A | E8: =IF($AF$14="2025",VLOOKUP($B8,GTMI_Groups!$B$2:$M$199,4,FALSE),IF($AF$14="2022",VLOOKUP((" "&$B8&" "),GTMI_Data!$B$2:$QN$595,447,FALSE),IF($AF$14="2020",VLOOKUP((" "&$B8&" "),GTMI_Data!$B$2:$QN$595,447,FALSE),"-"))) -> 0.75305889 | F8: =IF($AF$14="2025",VLOOKUP($B8,GTMI_Groups!$B$2:$M$199,5,FALSE),IF($AF$14="2022",VLOOKUP((" "&$B8&" "),GTMI_Data!$B$2:$QN$595,448,FALSE),IF($AF$14="2020",VLOOKUP((" "&$B8&" "),GTMI_Data!$B$2:$QN$595,448,FALSE),"-"))) -> A | G8: =IF($AF$14="2025",VLOOKUP($B8,GTMI_Groups!$B$2:$M$199,6,FALSE),IF($AF$14="2022",VLOOKUP((" "&$B8&" "),GTMI_Data!$B$2:$QN$595,449,FALSE),IF($AF$14="2020",VLOOKUP((" "&$B8&" "),GTMI_Data!$B$2:$QN$595,449,FALSE),"-"))) -> 0.78884017 | H8: =IF($AF$14="2025",VLOOKUP($B8,GTMI_Groups!$B$2:$M$199,7,FALSE),IF($AF$14="2022",VLOOKUP((" "&$B8&" "),GTMI_Data!$B$2:$QN$595,450,FALSE),IF($AF$14="2020",VLOOKUP((" "&$B8&" "),GTMI_Data!$B$2:$QN$595,450,FALSE),"-"))) -> A | I8: =IF($AF$14="2025",VLOOKUP($B8,GTMI_Groups!$B$2:$M$199,8,FALSE),IF($AF$14="2022",VLOOKUP((" "&$B8&" "),GTMI_Data!$B$2:$QN$595,451,FALSE),IF($AF$14="2020",VLOOKUP((" "&$B8&" "),GTMI_Data!$B$2:$QN$595,451,FALSE),"-"))) -> 0.90659494 | J8: =IF($AF$14="2025",VLOOKUP($B8,GTMI_Groups!$B$2:$M$199,9,FALSE),IF($AF$14="2022",VLOOKUP((" "&$B8&" "),GTMI_Data!$B$2:$QN$595,452,FALSE),IF($AF$14="2020",VLOOKUP((" "&$B8&" "),GTMI_Data!$B$2:$QN$595,452,FALSE),"-"))) -> B | K8: =IF($AF$14="2025",VLOOKUP($B8,GTMI_Groups!$B$2:$M$199,10,FALSE),IF($AF$14="2022",VLOOKUP((" "&$B8&" "),GTMI_Data!$B$2:$QN$595,453,FALSE),IF($AF$14="2020",VLOOKUP((" "&$B8&" "),GTMI_Data!$B$2:$QN$595,453,FALSE),"-"))) -> 0.64001805 | L8: =IF($AF$14="2025",VLOOKUP($B8,GTMI_Groups!$B$2:$M$199,11,FALSE),IF($AF$14="2022",VLOOKUP((" "&$B8&" "),GTMI_Data!$B$2:$QN$595,454,FALSE),IF($AF$14="2020",VLOOKUP((" "&$B8&" "),GTMI_Data!$B$2:$QN$595,454,FALSE),"-"))) -> B | M8: =IF($AF$14="2025",VLOOKUP($B8,GTMI_Groups!$B$2:$M$199,12,FALSE),IF($AF$14="2022",VLOOKUP((" "&$B8&" "),GTMI_Data!$B$2:$QN$595,455,FALSE),IF($AF$14="2020",VLOOKUP((" "&$B8&" "),GTMI_Data!$B$2:$QN$595,455,FALSE),"-"))) -> 0.67678243 | N8: =IF($AF$14="2025",VLOOKUP($B8,GTMI_Data!$B$2:$PR$595,427,FALSE),IF($AF$14="2022",VLOOKUP((" "&$B8&" "),GTMI_Data!$B$2:$QN$595,427,FALSE),IF($AF$14="2020",VLOOKUP((" "&$B8&" "),GTMI_Data!$B$2:$QN$595,427,FALSE),"-"))) -> S | O8: =IF($AF$14="2025",VLOOKUP($B8,GTMI_Data!$B$2:$PR$595,428,FALSE),IF($AF$14="2022",VLOOKUP((" "&$B8&" "),GTMI_Data!$B$2:$QN$595,428,FALSE),IF($AF$14="2020",VLOOKUP((" "&$B8&" "),GTMI_Data!$B$2:$QN$595,428,FALSE),"-"))) -> LCR | P8: =IF($AF$14="2025",VLOOKUP($B8,GTMI_Data!$B$2:$PR$595,429,FALSE),IF($AF$14="2022",VLOOKUP((" "&$B8&" "),GTMI_Data!$B$2:$QN$595,429,FALSE),IF($AF$14="2020",VLOOKUP((" "&$B8&" "),GTMI_Data!$B$2:$QN$595,429,FALSE),"-"))) -> UM | Q8: =IF($AF$14="2025",VLOOKUP($B8,GTMI_Data!$B$2:$PR$595,430,FALSE),IF($AF$14="2022",VLOOKUP((" "&$B8&" "),GTMI_Data!$B$2:$QN$595,430,FALSE),IF($AF$14="2020",VLOOKUP((" "&$B8&" "),GTMI_Data!$B$2:$QN$595,430,FALSE),"-"))) -> - | R8: =IF($AF$14="2025",VLOOKUP($B8,GTMI_Data!$B$2:$PR$595,431,FALSE),IF($AF$14="2022",VLOOKUP((" "&$B8&" "),GTMI_Data!$B$2:$QN$595,431,FALSE),IF($AF$14="2020",VLOOKUP((" "&$B8&" "),GTMI_Data!$B$2:$QN$595,431,FALSE),"-"))) -> IBRD | S8: =IF($AF$14="2025",VLOOKUP($B8,GTMI_Data!$B$2:$PR$595,432,FALSE),IF($AF$14="2022",VLOOKUP((" "&$B8&" "),GTMI_Data!$B$2:$QN$595,432,FALSE),IF($AF$14="2020",VLOOKUP((" "&$B8&" "),GTMI_Data!$B$2:$QN$595,432,FALSE),"-")))/1000 -> 45.538401 | T8: =IF($AF$14="2025",VLOOKUP($B8,GTMI_Data!$B$2:$PR$595,433,FALSE),IF($AF$14="2022",VLOOKUP((" "&$B8&" "),GTMI_Data!$B$2:$QN$595,433,FALSE),IF($AF$14="2020",VLOOKUP((" "&$B8&" "),GTMI_Data!$B$2:$QN$595,433,FALSE),"-"))) -> 0
A9: ECA | B9: ARM | C9: Armenia | D9: =IF($AF$14="2025",VLOOKUP($B9,GTMI_Groups!$B$2:$M$199,3,FALSE),IF($AF$14="2022",VLOOKUP((" "&$B9&" "),GTMI_Data!$B$2:$QN$595,446,FALSE),IF($AF$14="2020",VLOOKUP((" "&$B9&" "),GTMI_Data!$B$2:$QN$595,446,FALSE),"-"))) -> A | E9: =IF($AF$14="2025",VLOOKUP($B9,GTMI_Groups!$B$2:$M$199,4,FALSE),IF($AF$14="2022",VLOOKUP((" "&$B9&" "),GTMI_Data!$B$2:$QN$595,447,FALSE),IF($AF$14="2020",VLOOKUP((" "&$B9&" "),GTMI_Data!$B$2:$QN$595,447,FALSE),"-"))) -> 0.76901278 | F9: =IF($AF$14="2025",VLOOKUP($B9,GTMI_Groups!$B$2:$M$199,5,FALSE),IF($AF$14="2022",VLOOKUP((" "&$B9&" "),GTMI_Data!$B$2:$QN$595,448,FALSE),IF($AF$14="2020",VLOOKUP((" "&$B9&" "),GTMI_Data!$B$2:$QN$595,448,FALSE),"-"))) -> A | G9: =IF($AF$14="2025",VLOOKUP($B9,GTMI_Groups!$B$2:$M$199,6,FALSE),IF($AF$14="2022",VLOOKUP((" "&$B9&" "),GTMI_Data!$B$2:$QN$595,449,FALSE),IF($AF$14="2020",VLOOKUP((" "&$B9&" "),GTMI_Data!$B$2:$QN$595,449,FALSE),"-"))) -> 0.78024432 | H9: =IF($AF$14="2025",VLOOKUP($B9,GTMI_Groups!$B$2:$M$199,7,FALSE),IF($AF$14="2022",VLOOKUP((" "&$B9&" "),GTMI_Data!$B$2:$QN$595,450,FALSE),IF($AF$14="2020",VLOOKUP((" "&$B9&" "),GTMI_Data!$B$2:$QN$595,450,FALSE),"-"))) -> A | I9: =IF($AF$14="2025",VLOOKUP($B9,GTMI_Groups!$B$2:$M$199,8,FALSE),IF($AF$14="2022",VLOOKUP((" "&$B9&" "),GTMI_Data!$B$2:$QN$595,451,FALSE),IF($AF$14="2020",VLOOKUP((" "&$B9&" "),GTMI_Data!$B$2:$QN$595,451,FALSE),"-"))) -> 0.81229714 | J9: =IF($AF$14="2025",VLOOKUP($B9,GTMI_Groups!$B$2:$M$199,9,FALSE),IF($AF$14="2022",VLOOKUP((" "&$B9&" "),GTMI_Data!$B$2:$QN$595,452,FALSE),IF($AF$14="2020",VLOOKUP((" "&$B9&" "),GTMI_Data!$B$2:$QN$595,452,FALSE),"-"))) -> A | K9: =IF($AF$14="2025",VLOOKUP($B9,GTMI_Groups!$B$2:$M$199,10,FALSE),IF($AF$14="2022",VLOOKUP((" "&$B9&" "),GTMI_Data!$B$2:$QN$595,453,FALSE),IF($AF$14="2020",VLOOKUP((" "&$B9&" "),GTMI_Data!$B$2:$QN$595,453,FALSE),"-"))) -> 0.7547609 | L9: =IF($AF$14="2025",VLOOKUP($B9,GTMI_Groups!$B$2:$M$199,11,FALSE),IF($AF$14="2022",VLOOKUP((" "&$B9&" "),GTMI_Data!$B$2:$QN$595,454,FALSE),IF($AF$14="2020",VLOOKUP((" "&$B9&" "),GTMI_Data!$B$2:$QN$595,454,FALSE),"-"))) -> B | M9: =IF($AF$14="2025",VLOOKUP($B9,GTMI_Groups!$B$2:$M$199,12,FALSE),IF($AF$14="2022",VLOOKUP((" "&$B9&" "),GTMI_Data!$B$2:$QN$595,455,FALSE),IF($AF$14="2020",VLOOKUP((" "&$B9&" "),GTMI_Data!$B$2:$QN$595,455,FALSE),"-"))) -> 0.72874874 | N9: =IF($AF$14="2025",VLOOKUP($B9,GTMI_Data!$B$2:$PR$595,427,FALSE),IF($AF$14="2022",VLOOKUP((" "&$B9&" "),GTMI_Data!$B$2:$QN$595,427,FALSE),IF($AF$14="2020",VLOOKUP((" "&$B9&" "),GTMI_Data!$B$2:$QN$595,427,FALSE),"-"))) -> S | O9: =IF($AF$14="2025",VLOOKUP($B9,GTMI_Data!$B$2:$PR$595,428,FALSE),IF($AF$14="2022",VLOOKUP((" "&$B9&" "),GTMI_Data!$B$2:$QN$595,428,FALSE),IF($AF$14="2020",VLOOKUP((" "&$B9&" "),GTMI_Data!$B$2:$QN$595,428,FALSE),"-"))) -> ECA | P9: =IF($AF$14="2025",VLOOKUP($B9,GTMI_Data!$B$2:$PR$595,429,FALSE),IF($AF$14="2022",VLOOKUP((" "&$B9&" "),GTMI_Data!$B$2:$QN$595,429,FALSE),IF($AF$14="2020",VLOOKUP((" "&$B9&" "),GTMI_Data!$B$2:$QN$595,429,FALSE),"-"))) -> UM | Q9: =IF($AF$14="2025",VLOOKUP($B9,GTMI_Data!$B$2:$PR$595,430,FALSE),IF($AF$14="2022",VLOOKUP((" "&$B9&" "),GTMI_Data!$B$2:$QN$595,430,FALSE),IF($AF$14="2020",VLOOKUP((" "&$B9&" "),GTMI_Data!$B$2:$QN$595,430,FALSE),"-"))) -> - | R9: =IF($AF$14="2025",VLOOKUP($B9,GTMI_Data!$B$2:$PR$595,431,FALSE),IF($AF$14="2022",VLOOKUP((" "&$B9&" "),GTMI_Data!$B$2:$QN$595,431,FALSE),IF($AF$14="2020",VLOOKUP((" "&$B9&" "),GTMI_Data!$B$2:$QN$595,431,FALSE),"-"))) -> IBRD | S9: =IF($AF$14="2025",VLOOKUP($B9,GTMI_Data!$B$2:$PR$595,432,FALSE),IF($AF$14="2022",VLOOKUP((" "&$B9&" "),GTMI_Data!$B$2:$QN$595,432,FALSE),IF($AF$14="2020",VLOOKUP((" "&$B9&" "),GTMI_Data!$B$2:$QN$595,432,FALSE),"-")))/1000 -> 2.943393 | T9: =IF($AF$14="2025",VLOOKUP($B9,GTMI_Data!$B$2:$PR$595,433,FALSE),IF($AF$14="2022",VLOOKUP((" "&$B9&" "),GTMI_Data!$B$2:$QN$595,433,FALSE),IF($AF$14="2020",VLOOKUP((" "&$B9&" "),GTMI_Data!$B$2:$QN$595,433,FALSE),"-"))) -> 0
A10: - | B10: AUS | C10: Australia | D10: =IF($AF$14="2025",VLOOKUP($B10,GTMI_Groups!$B$2:$M$199,3,FALSE),IF($AF$14="2022",VLOOKUP((" "&$B10&" "),GTMI_Data!$B$2:$QN$595,446,FALSE),IF($AF$14="2020",VLOOKUP((" "&$B10&" "),GTMI_Data!$B$2:$QN$595,446,FALSE),"-"))) -> A | E10: =IF($AF$14="2025",VLOOKUP($B10,GTMI_Groups!$B$2:$M$199,4,FALSE),IF($AF$14="2022",VLOOKUP((" "&$B10&" "),GTMI_Data!$B$2:$QN$595,447,FALSE),IF($AF$14="2020",VLOOKUP((" "&$B10&" "),GTMI_Data!$B$2:$QN$595,447,FALSE),"-"))) -> 0.98495271 | F10: =IF($AF$14="2025",VLOOKUP($B10,GTMI_Groups!$B$2:$M$199,5,FALSE),IF($AF$14="2022",VLOOKUP((" "&$B10&" "),GTMI_Data!$B$2:$QN$595,448,FALSE),IF($AF$14="2020",VLOOKUP((" "&$B10&" "),GTMI_Data!$B$2:$QN$595,448,FALSE),"-"))) -> A | G10: =IF($AF$14="2025",VLOOKUP($B10,GTMI_Groups!$B$2:$M$199,6,FALSE),IF($AF$14="2022",VLOOKUP((" "&$B10&" "),GTMI_Data!$B$2:$QN$595,449,FALSE),IF($AF$14="2020",VLOOKUP((" "&$B10&" "),GTMI_Data!$B$2:$QN$595,449,FALSE),"-"))) -> 0.98925743 | H10: =IF($AF$14="2025",VLOOKUP($B10,GTMI_Groups!$B$2:$M$199,7,FALSE),IF($AF$14="2022",VLOOKUP((" "&$B10&" "),GTMI_Data!$B$2:$QN$595,450,FALSE),IF($AF$14="2020",VLOOKUP((" "&$B10&" "),GTMI_Data!$B$2:$QN$595,450,FALSE),"-"))) -> A | I10: =IF($AF$14="2025",VLOOKUP($B10,GTMI_Groups!$B$2:$M$199,8,FALSE),IF($AF$14="2022",VLOOKUP((" "&$B10&" "),GTMI_Data!$B$2:$QN$595,451,FALSE),IF($AF$14="2020",VLOOKUP((" "&$B10&" "),GTMI_Data!$B$2:$QN$595,451,FALSE),"-"))) -> 0.9923778 | J10: =IF($AF$14="2025",VLOOKUP($B10,GTMI_Groups!$B$2:$M$199,9,FALSE),IF($AF$14="2022",VLOOKUP((" "&$B10&" "),GTMI_Data!$B$2:$QN$595,452,FALSE),IF($AF$14="2020",VLOOKUP((" "&$B10&" "),GTMI_Data!$B$2:$QN$595,452,FALSE),"-"))) -> A | K10: =IF($AF$14="2025",VLOOKUP($B10,GTMI_Groups!$B$2:$M$199,10,FALSE),IF($AF$14="2022",VLOOKUP((" "&$B10&" "),GTMI_Data!$B$2:$QN$595,453,FALSE),IF($AF$14="2020",VLOOKUP((" "&$B10&" "),GTMI_Data!$B$2:$QN$595,453,FALSE),"-"))) -> 0.9602406 | L10: =IF($AF$14="2025",VLOOKUP($B10,GTMI_Groups!$B$2:$M$199,11,FALSE),IF($AF$14="2022",VLOOKUP((" "&$B10&" "),GTMI_Data!$B$2:$QN$595,454,FALSE),IF($AF$14="2020",VLOOKUP((" "&$B10&" "),GTMI_Data!$B$2:$QN$595,454,FALSE),"-"))) -> A | M10: =IF($AF$14="2025",VLOOKUP($B10,GTMI_Groups!$B$2:$M$199,12,FALSE),IF($AF$14="2022",VLOOKUP((" "&$B10&" "),GTMI_Data!$B$2:$QN$595,455,FALSE),IF($AF$14="2020",VLOOKUP((" "&$B10&" "),GTMI_Data!$B$2:$QN$595,455,FALSE),"-"))) -> 0.99793501 | N10: =IF($AF$14="2025",VLOOKUP($B10,GTMI_Data!$B$2:$PR$595,427,FALSE),IF($AF$14="2022",VLOOKUP((" "&$B10&" "),GTMI_Data!$B$2:$QN$595,427,FALSE),IF($AF$14="2020",VLOOKUP((" "&$B10&" "),GTMI_Data!$B$2:$QN$595,427,FALSE),"-"))) -> S | O10: =IF($AF$14="2025",VLOOKUP($B10,GTMI_Data!$B$2:$PR$595,428,FALSE),IF($AF$14="2022",VLOOKUP((" "&$B10&" "),GTMI_Data!$B$2:$QN$595,428,FALSE),IF($AF$14="2020",VLOOKUP((" "&$B10&" "),GTMI_Data!$B$2:$QN$595,428,FALSE),"-"))) -> EAP | P10: =IF($AF$14="2025",VLOOKUP($B10,GTMI_Data!$B$2:$PR$595,429,FALSE),IF($AF$14="2022",VLOOKUP((" "&$B10&" "),GTMI_Data!$B$2:$QN$595,429,FALSE),IF($AF$14="2020",VLOOKUP((" "&$B10&" "),GTMI_Data!$B$2:$QN$595,429,FALSE),"-"))) -> H | Q10: =IF($AF$14="2025",VLOOKUP($B10,GTMI_Data!$B$2:$PR$595,430,FALSE),IF($AF$14="2022",VLOOKUP((" "&$B10&" "),GTMI_Data!$B$2:$QN$595,430,FALSE),IF($AF$14="2020",VLOOKUP((" "&$B10&" "),GTMI_Data!$B$2:$QN$595,430,FALSE),"-"))) -> - | R10: =IF($AF$14="2025",VLOOKUP($B10,GTMI_Data!$B$2:$PR$595,431,FALSE),IF($AF$14="2022",VLOOKUP((" "&$B10&" "),GTMI_Data!$B$2:$QN$595,431,FALSE),IF($AF$14="2020",VLOOKUP((" "&$B10&" "),GTMI_Data!$B$2:$QN$595,431,FALSE),"-"))) -> - | S10: =IF($AF$14="2025",VLOOKUP($B10,GTMI_Data!$B$2:$PR$595,432,FALSE),IF($AF$14="2022",VLOOKUP((" "&$B10&" "),GTMI_Data!$B$2:$QN$595,432,FALSE),IF($AF$14="2020",VLOOKUP((" "&$B10&" "),GTMI_Data!$B$2:$QN$595,432,FALSE),"-")))/1000 -> 26.451124 | T10: =IF($AF$14="2025",VLOOKUP($B10,GTMI_Data!$B$2:$PR$595,433,FALSE),IF($AF$14="2022",VLOOKUP((" "&$B10&" "),GTMI_Data!$B$2:$QN$595,433,FALSE),IF($AF$14="2020",VLOOKUP((" "&$B10&" "),GTMI_Data!$B$2:$QN$595,433,FALSE),"-"))) -> 0
A11: - | B11: AUT | C11: Austria | D11: =IF($AF$14="2025",VLOOKUP($B11,GTMI_Groups!$B$2:$M$199,3,FALSE),IF($AF$14="2022",VLOOKUP((" "&$B11&" "),GTMI_Data!$B$2:$QN$595,446,FALSE),IF($AF$14="2020",VLOOKUP((" "&$B11&" "),GTMI_Data!$B$2:$QN$595,446,FALSE),"-"))) -> A | E11: =IF($AF$14="2025",VLOOKUP($B11,GTMI_Groups!$B$2:$M$199,4,FALSE),IF($AF$14="2022",VLOOKUP((" "&$B11&" "),GTMI_Data!$B$2:$QN$595,447,FALSE),IF($AF$14="2020",VLOOKUP((" "&$B11&" "),GTMI_Data!$B$2:$QN$595,447,FALSE),"-"))) -> 0.92904049 | F11: =IF($AF$14="2025",VLOOKUP($B11,GTMI_Groups!$B$2:$M$199,5,FALSE),IF($AF$14="2022",VLOOKUP((" "&$B11&" "),GTMI_Data!$B$2:$QN$595,448,FALSE),IF($AF$14="2020",VLOOKUP((" "&$B11&" "),GTMI_Data!$B$2:$QN$595,448,FALSE),"-"))) -> A | G11: =IF($AF$14="2025",VLOOKUP($B11,GTMI_Groups!$B$2:$M$199,6,FALSE),IF($AF$14="2022",VLOOKUP((" "&$B11&" "),GTMI_Data!$B$2:$QN$595,449,FALSE),IF($AF$14="2020",VLOOKUP((" "&$B11&" "),GTMI_Data!$B$2:$QN$595,449,FALSE),"-"))) -> 0.95133411 | H11: =IF($AF$14="2025",VLOOKUP($B11,GTMI_Groups!$B$2:$M$199,7,FALSE),IF($AF$14="2022",VLOOKUP((" "&$B11&" "),GTMI_Data!$B$2:$QN$595,450,FALSE),IF($AF$14="2020",VLOOKUP((" "&$B11&" "),GTMI_Data!$B$2:$QN$595,450,FALSE),"-"))) -> A | I11: =IF($AF$14="2025",VLOOKUP($B11,GTMI_Groups!$B$2:$M$199,8,FALSE),IF($AF$14="2022",VLOOKUP((" "&$B11&" "),GTMI_Data!$B$2:$QN$595,451,FALSE),IF($AF$14="2020",VLOOKUP((" "&$B11&" "),GTMI_Data!$B$2:$QN$595,451,FALSE),"-"))) -> 0.97599576 | J11: =IF($AF$14="2025",VLOOKUP($B11,GTMI_Groups!$B$2:$M$199,9,FALSE),IF($AF$14="2022",VLOOKUP((" "&$B11&" "),GTMI_Data!$B$2:$QN$595,452,FALSE),IF($AF$14="2020",VLOOKUP((" "&$B11&" "),GTMI_Data!$B$2:$QN$595,452,FALSE),"-"))) -> A | K11: =IF($AF$14="2025",VLOOKUP($B11,GTMI_Groups!$B$2:$M$199,10,FALSE),IF($AF$14="2022",VLOOKUP((" "&$B11&" "),GTMI_Data!$B$2:$QN$595,453,FALSE),IF($AF$14="2020",VLOOKUP((" "&$B11&" "),GTMI_Data!$B$2:$QN$595,453,FALSE),"-"))) -> 0.85518195 | L11: =IF($AF$14="2025",VLOOKUP($B11,GTMI_Groups!$B$2:$M$199,11,FALSE),IF($AF$14="2022",VLOOKUP((" "&$B11&" "),GTMI_Data!$B$2:$QN$595,454,FALSE),IF($AF$14="2020",VLOOKUP((" "&$B11&" "),GTMI_Data!$B$2:$QN$595,454,FALSE),"-"))) -> A | M11: =IF($AF$14="2025",VLOOKUP($B11,GTMI_Groups!$B$2:$M$199,12,FALSE),IF($AF$14="2022",VLOOKUP((" "&$B11&" "),GTMI_Data!$B$2:$QN$595,455,FALSE),IF($AF$14="2020",VLOOKUP((" "&$B11&" "),GTMI_Data!$B$2:$QN$595,455,FALSE),"-"))) -> 0.93365016 | N11: =IF($AF$14="2025",VLOOKUP($B11,GTMI_Data!$B$2:$PR$595,427,FALSE),IF($AF$14="2022",VLOOKUP((" "&$B11&" "),GTMI_Data!$B$2:$QN$595,427,FALSE),IF($AF$14="2020",VLOOKUP((" "&$B11&" "),GTMI_Data!$B$2:$QN$595,427,FALSE),"-"))) -> S | O11: =IF($AF$14="2025",VLOOKUP($B11,GTMI_Data!$B$2:$PR$595,428,FALSE),IF($AF$14="2022",VLOOKUP((" "&$B11&" "),GTMI_Data!$B$2:$QN$595,428,FALSE),IF($AF$14="2020",VLOOKUP((" "&$B11&" "),GTMI_Data!$B$2:$QN$595,428,FALSE),"-"))) -> ECA | P11: =IF($AF$14="2025",VLOOKUP($B11,GTMI_Data!$B$2:$PR$595,429,FALSE),IF($AF$14="2022",VLOOKUP((" "&$B11&" "),GTMI_Data!$B$2:$QN$595,429,FALSE),IF($AF$14="2020",VLOOKUP((" "&$B11&" "),GTMI_Data!$B$2:$QN$595,429,FALSE),"-"))) -> H | Q11: =IF($AF$14="2025",VLOOKUP($B11,GTMI_Data!$B$2:$PR$595,430,FALSE),IF($AF$14="2022",VLOOKUP((" "&$B11&" "),GTMI_Data!$B$2:$QN$595,430,FALSE),IF($AF$14="2020",VLOOKUP((" "&$B11&" "),GTMI_Data!$B$2:$QN$595,430,FALSE),"-"))) -> - | R11: =IF($AF$14="2025",VLOOKUP($B11,GTMI_Data!$B$2:$PR$595,431,FALSE),IF($AF$14="2022",VLOOKUP((" "&$B11&" "),GTMI_Data!$B$2:$QN$595,431,FALSE),IF($AF$14="2020",VLOOKUP((" "&$B11&" "),GTMI_Data!$B$2:$QN$595,431,FALSE),"-"))) -> - | S11: =IF($AF$14="2025",VLOOKUP($B11,GTMI_Data!$B$2:$PR$595,432,FALSE),IF($AF$14="2022",VLOOKUP((" "&$B11&" "),GTMI_Data!$B$2:$QN$595,432,FALSE),IF($AF$14="2020",VLOOKUP((" "&$B11&" "),GTMI_Data!$B$2:$QN$595,432,FALSE),"-")))/1000 -> 9.130429 | T11: =IF($AF$14="2025",VLOOKUP($B11,GTMI_Data!$B$2:$PR$595,433,FALSE),IF($AF$14="2022",VLOOKUP((" "&$B11&" "),GTMI_Data!$B$2:$QN$595,433,FALSE),IF($AF$14="2020",VLOOKUP((" "&$B11&" "),GTMI_Data!$B$2:$QN$595,433,FALSE),"-"))) -> 0
A12: ECA | B12: AZE | C12: Azerbaijan | D12: =IF($AF$14="2025",VLOOKUP($B12,GTMI_Groups!$B$2:$M$199,3,FALSE),IF($AF$14="2022",VLOOKUP((" "&$B12&" "),GTMI_Data!$B$2:$QN$595,446,FALSE),IF($AF$14="2020",VLOOKUP((" "&$B12&" "),GTMI_Data!$B$2:$QN$595,446,FALSE),"-"))) -> A | E12: =IF($AF$14="2025",VLOOKUP($B12,GTMI_Groups!$B$2:$M$199,4,FALSE),IF($AF$14="2022",VLOOKUP((" "&$B12&" "),GTMI_Data!$B$2:$QN$595,447,FALSE),IF($AF$14="2020",VLOOKUP((" "&$B12&" "),GTMI_Data!$B$2:$QN$595,447,FALSE),"-"))) -> 0.76886315 | F12: =IF($AF$14="2025",VLOOKUP($B12,GTMI_Groups!$B$2:$M$199,5,FALSE),IF($AF$14="2022",VLOOKUP((" "&$B12&" "),GTMI_Data!$B$2:$QN$595,448,FALSE),IF($AF$14="2020",VLOOKUP((" "&$B12&" "),GTMI_Data!$B$2:$QN$595,448,FALSE),"-"))) -> A | G12: =IF($AF$14="2025",VLOOKUP($B12,GTMI_Groups!$B$2:$M$199,6,FALSE),IF($AF$14="2022",VLOOKUP((" "&$B12&" "),GTMI_Data!$B$2:$QN$595,449,FALSE),IF($AF$14="2020",VLOOKUP((" "&$B12&" "),GTMI_Data!$B$2:$QN$595,449,FALSE),"-"))) -> 0.92051485 | H12: =IF($AF$14="2025",VLOOKUP($B12,GTMI_Groups!$B$2:$M$199,7,FALSE),IF($AF$14="2022",VLOOKUP((" "&$B12&" "),GTMI_Data!$B$2:$QN$595,450,FALSE),IF($AF$14="2020",VLOOKUP((" "&$B12&" "),GTMI_Data!$B$2:$QN$595,450,FALSE),"-"))) -> A | I12: =IF($AF$14="2025",VLOOKUP($B12,GTMI_Groups!$B$2:$M$199,8,FALSE),IF($AF$14="2022",VLOOKUP((" "&$B12&" "),GTMI_Data!$B$2:$QN$595,451,FALSE),IF($AF$14="2020",VLOOKUP((" "&$B12&" "),GTMI_Data!$B$2:$QN$595,451,FALSE),"-"))) -> 0.97439641 | J12: =IF($AF$14="2025",VLOOKUP($B12,GTMI_Groups!$B$2:$M$199,9,FALSE),IF($AF$14="2022",VLOOKUP((" "&$B12&" "),GTMI_Data!$B$2:$QN$595,452,FALSE),IF($AF$14="2020",VLOOKUP((" "&$B12&" "),GTMI_Data!$B$2:$QN$595,452,FALSE),"-"))) -> C | K12: =IF($AF$14="2025",VLOOKUP($B12,GTMI_Groups!$B$2:$M$199,10,FALSE),IF($AF$14="2022",VLOOKUP((" "&$B12&" "),GTMI_Data!$B$2:$QN$595,453,FALSE),IF($AF$14="2020",VLOOKUP((" "&$B12&" "),GTMI_Data!$B$2:$QN$595,453,FALSE),"-"))) -> 0.38223158 | L12: =IF($AF$14="2025",VLOOKUP($B12,GTMI_Groups!$B$2:$M$199,11,FALSE),IF($AF$14="2022",VLOOKUP((" "&$B12&" "),GTMI_Data!$B$2:$QN$595,454,FALSE),IF($AF$14="2020",VLOOKUP((" "&$B12&" "),GTMI_Data!$B$2:$QN$595,454,FALSE),"-"))) -> A | M12: =IF($AF$14="2025",VLOOKUP($B12,GTMI_Groups!$B$2:$M$199,12,FALSE),IF($AF$14="2022",VLOOKUP((" "&$B12&" "),GTMI_Data!$B$2:$QN$595,455,FALSE),IF($AF$14="2020",VLOOKUP((" "&$B12&" "),GTMI_Data!$B$2:$QN$595,455,FALSE),"-"))) -> 0.79830975 | N12: =IF($AF$14="2025",VLOOKUP($B12,GTMI_Data!$B$2:$PR$595,427,FALSE),IF($AF$14="2022",VLOOKUP((" "&$B12&" "),GTMI_Data!$B$2:$QN$595,427,FALSE),IF($AF$14="2020",VLOOKUP((" "&$B12&" "),GTMI_Data!$B$2:$QN$595,427,FALSE),"-"))) -> S | O12: =IF($AF$14="2025",VLOOKUP($B12,GTMI_Data!$B$2:$PR$595,428,FALSE),IF($AF$14="2022",VLOOKUP((" "&$B12&" "),GTMI_Data!$B$2:$QN$595,428,FALSE),IF($AF$14="2020",VLOOKUP((" "&$B12&" "),GTMI_Data!$B$2:$QN$595,428,FALSE),"-"))) -> ECA | P12: =IF($AF$14="2025",VLOOKUP($B12,GTMI_Data!$B$2:$PR$595,429,FALSE),IF($AF$14="2022",VLOOKUP((" "&$B12&" "),GTMI_Data!$B$2:$QN$595,429,FALSE),IF($AF$14="2020",VLOOKUP((" "&$B12&" "),GTMI_Data!$B$2:$QN$595,429,FALSE),"-"))) -> UM | Q12: =IF($AF$14="2025",VLOOKUP($B12,GTMI_Data!$B$2:$PR$595,430,FALSE),IF($AF$14="2022",VLOOKUP((" "&$B12&" "),GTMI_Data!$B$2:$QN$595,430,FALSE),IF($AF$14="2020",VLOOKUP((" "&$B12&" "),GTMI_Data!$B$2:$QN$595,430,FALSE),"-"))) -> - | R12: =IF($AF$14="2025",VLOOKUP($B12,GTMI_Data!$B$2:$PR$595,431,FALSE),IF($AF$14="2022",VLOOKUP((" "&$B12&" "),GTMI_Data!$B$2:$QN$595,431,FALSE),IF($AF$14="2020",VLOOKUP((" "&$B12&" "),GTMI_Data!$B$2:$QN$595,431,FALSE),"-"))) -> IBRD | S12: =IF($AF$14="2025",VLOOKUP($B12,GTMI_Data!$B$2:$PR$595,432,FALSE),IF($AF$14="2022",VLOOKUP((" "&$B12&" "),GTMI_Data!$B$2:$QN$595,432,FALSE),IF($AF$14="2020",VLOOKUP((" "&$B12&" "),GTMI_Data!$B$2:$QN$595,432,FALSE),"-")))/1000 -> 10.318207 | T12: =IF($AF$14="2025",VLOOKUP($B12,GTMI_Data!$B$2:$PR$595,433,FALSE),IF($AF$14="2022",VLOOKUP((" "&$B12&" "),GTMI_Data!$B$2:$QN$595,433,FALSE),IF($AF$14="2020",VLOOKUP((" "&$B12&" "),GTMI_Data!$B$2:$QN$595,433,FALSE),"-"))) -> 0
A13: LCR | B13: BHS | C13: Bahamas | D13: =IF($AF$14="2025",VLOOKUP($B13,GTMI_Groups!$B$2:$M$199,3,FALSE),IF($AF$14="2022",VLOOKUP((" "&$B13&" "),GTMI_Data!$B$2:$QN$595,446,FALSE),IF($AF$14="2020",VLOOKUP((" "&$B13&" "),GTMI_Data!$B$2:$QN$595,446,FALSE),"-"))) -> B | E13: =IF($AF$14="2025",VLOOKUP($B13,GTMI_Groups!$B$2:$M$199,4,FALSE),IF($AF$14="2022",VLOOKUP((" "&$B13&" "),GTMI_Data!$B$2:$QN$595,447,FALSE),IF($AF$14="2020",VLOOKUP((" "&$B13&" "),GTMI_Data!$B$2:$QN$595,447,FALSE),"-"))) -> 0.50225716 | F13: =IF($AF$14="2025",VLOOKUP($B13,GTMI_Groups!$B$2:$M$199,5,FALSE),IF($AF$14="2022",VLOOKUP((" "&$B13&" "),GTMI_Data!$B$2:$QN$595,448,FALSE),IF($AF$14="2020",VLOOKUP((" "&$B13&" "),GTMI_Data!$B$2:$QN$595,448,FALSE),"-"))) -> B | G13: =IF($AF$14="2025",VLOOKUP($B13,GTMI_Groups!$B$2:$M$199,6,FALSE),IF($AF$14="2022",VLOOKUP((" "&$B13&" "),GTMI_Data!$B$2:$QN$595,449,FALSE),IF($AF$14="2020",VLOOKUP((" "&$B13&" "),GTMI_Data!$B$2:$QN$595,449,FALSE),"-"))) -> 0.57212714 | H13: =IF($AF$14="2025",VLOOKUP($B13,GTMI_Groups!$B$2:$M$199,7,FALSE),IF($AF$14="2022",VLOOKUP((" "&$B13&" "),GTMI_Data!$B$2:$QN$595,450,FALSE),IF($AF$14="2020",VLOOKUP((" "&$B13&" "),GTMI_Data!$B$2:$QN$595,450,FALSE),"-"))) -> B | I13: =IF($AF$14="2025",VLOOKUP($B13,GTMI_Groups!$B$2:$M$199,8,FALSE),IF($AF$14="2022",VLOOKUP((" "&$B13&" "),GTMI_Data!$B$2:$QN$595,451,FALSE),IF($AF$14="2020",VLOOKUP((" "&$B13&" "),GTMI_Data!$B$2:$QN$595,451,FALSE),"-"))) -> 0.73046955 | J13: =IF($AF$14="2025",VLOOKUP($B13,GTMI_Groups!$B$2:$M$199,9,FALSE),IF($AF$14="2022",VLOOKUP((" "&$B13&" "),GTMI_Data!$B$2:$QN$595,452,FALSE),IF($AF$14="2020",VLOOKUP((" "&$B13&" "),GTMI_Data!$B$2:$QN$595,452,FALSE),"-"))) -> D | K13: =IF($AF$14="2025",VLOOKUP($B13,GTMI_Groups!$B$2:$M$199,10,FALSE),IF($AF$14="2022",VLOOKUP((" "&$B13&" "),GTMI_Data!$B$2:$QN$595,453,FALSE),IF($AF$14="2020",VLOOKUP((" "&$B13&" "),GTMI_Data!$B$2:$QN$595,453,FALSE),"-"))) -> 0.16212331 | L13: =IF($AF$14="2025",VLOOKUP($B13,GTMI_Groups!$B$2:$M$199,11,FALSE),IF($AF$14="2022",VLOOKUP((" "&$B13&" "),GTMI_Data!$B$2:$QN$595,454,FALSE),IF($AF$14="2020",VLOOKUP((" "&$B13&" "),GTMI_Data!$B$2:$QN$595,454,FALSE),"-"))) -> B | M13: =IF($AF$14="2025",VLOOKUP($B13,GTMI_Groups!$B$2:$M$199,12,FALSE),IF($AF$14="2022",VLOOKUP((" "&$B13&" "),GTMI_Data!$B$2:$QN$595,455,FALSE),IF($AF$14="2020",VLOOKUP((" "&$B13&" "),GTMI_Data!$B$2:$QN$595,455,FALSE),"-"))) -> 0.54430865 | N13: =IF($AF$14="2025",VLOOKUP($B13,GTMI_Data!$B$2:$PR$595,427,FALSE),IF($AF$14="2022",VLOOKUP((" "&$B13&" "),GTMI_Data!$B$2:$QN$595,427,FALSE),IF($AF$14="2020",VLOOKUP((" "&$B13&" "),GTMI_Data!$B$2:$QN$595,427,FALSE),"-"))) -> S | O13: =IF($AF$14="2025",VLOOKUP($B13,GTMI_Data!$B$2:$PR$595,428,FALSE),IF($AF$14="2022",VLOOKUP((" "&$B13&" "),GTMI_Data!$B$2:$QN$595,428,FALSE),IF($AF$14="2020",VLOOKUP((" "&$B13&" "),GTMI_Data!$B$2:$QN$595,428,FALSE),"-"))) -> LCR | P13: =IF($AF$14="2025",VLOOKUP($B13,GTMI_Data!$B$2:$PR$595,429,FALSE),IF($AF$14="2022",VLOOKUP((" "&$B13&" "),GTMI_Data!$B$2:$QN$595,429,FALSE),IF($AF$14="2020",VLOOKUP((" "&$B13&" "),GTMI_Data!$B$2:$QN$595,429,FALSE),"-"))) -> H | Q13: =IF($AF$14="2025",VLOOKUP($B13,GTMI_Data!$B$2:$PR$595,430,FALSE),IF($AF$14="2022",VLOOKUP((" "&$B13&" "),GTMI_Data!$B$2:$QN$595,430,FALSE),IF($AF$14="2020",VLOOKUP((" "&$B13&" "),GTMI_Data!$B$2:$QN$595,430,FALSE),"-"))) -> - | R13: =IF($AF$14="2025",VLOOKUP($B13,GTMI_Data!$B$2:$PR$595,431,FALSE),IF($AF$14="2022",VLOOKUP((" "&$B13&" "),GTMI_Data!$B$2:$QN$595,431,FALSE),IF($AF$14="2020",VLOOKUP((" "&$B13&" "),GTMI_Data!$B$2:$QN$595,431,FALSE),"-"))) -> - | S13: =IF($AF$14="2025",VLOOKUP($B13,GTMI_Data!$B$2:$PR$595,432,FALSE),IF($AF$14="2022",VLOOKUP((" "&$B13&" "),GTMI_Data!$B$2:$QN$595,432,FALSE),IF($AF$14="2020",VLOOKUP((" "&$B13&" "),GTMI_Data!$B$2:$QN$595,432,FALSE),"-")))/1000 -> 0.39944 | T13: =IF($AF$14="2025",VLOOKUP($B13,GTMI_Data!$B$2:$PR$595,433,FALSE),IF($AF$14="2022",VLOOKUP((" "&$B13&" "),GTMI_Data!$B$2:$QN$595,433,FALSE),IF($AF$14="2020",VLOOKUP((" "&$B13&" "),GTMI_Data!$B$2:$QN$595,433,FALSE),"-"))) -> 1
... A30: AFW | B30: CPV | C30: Cabo Verde | D30: =IF($AF$14="2025",VLOOKUP($B30,GTMI_Groups!$B$2:$M$199,3,FALSE),IF($AF$14="2022",VLOOKUP((" "&$B30&" "),GTMI_Data!$B$2:$QN$595,446,FALSE),IF($AF$14="2020",VLOOKUP((" "&$B30&" "),GTMI_Data!$B$2:$QN$595,446,FALSE),"-"))) -> A | E30: =IF($AF$14="2025",VLOOKUP($B30,GTMI_Groups!$B$2:$M$199,4,FALSE),IF($AF$14="2022",VLOOKUP((" "&$B30&" "),GTMI_Data!$B$2:$QN$595,447,FALSE),IF($AF$14="2020",VLOOKUP((" "&$B30&" "),GTMI_Data!$B$2:$QN$595,447,FALSE),"-"))) -> 0.77412928 | F30: =IF($AF$14="2025",VLOOKUP($B30,GTMI_Groups!$B$2:$M$199,5,FALSE),IF($AF$14="2022",VLOOKUP((" "&$B30&" "),GTMI_Data!$B$2:$QN$595,448,FALSE),IF($AF$14="2020",VLOOKUP((" "&$B30&" "),GTMI_Data!$B$2:$QN$595,448,FALSE),"-"))) -> A | G30: =IF($AF$14="2025",VLOOKUP($B30,GTMI_Groups!$B$2:$M$199,6,FALSE),IF($AF$14="2022",VLOOKUP((" "&$B30&" "),GTMI_Data!$B$2:$QN$595,449,FALSE),IF($AF$14="2020",VLOOKUP((" "&$B30&" "),GTMI_Data!$B$2:$QN$595,449,FALSE),"-"))) -> 0.8022961 | H30: =IF($AF$14="2025",VLOOKUP($B30,GTMI_Groups!$B$2:$M$199,7,FALSE),IF($AF$14="2022",VLOOKUP((" "&$B30&" "),GTMI_Data!$B$2:$QN$595,450,FALSE),IF($AF$14="2020",VLOOKUP((" "&$B30&" "),GTMI_Data!$B$2:$QN$595,450,FALSE),"-"))) -> A | I30: =IF($AF$14="2025",VLOOKUP($B30,GTMI_Groups!$B$2:$M$199,8,FALSE),IF($AF$14="2022",VLOOKUP((" "&$B30&" "),GTMI_Data!$B$2:$QN$595,451,FALSE),IF($AF$14="2020",VLOOKUP((" "&$B30&" "),GTMI_Data!$B$2:$QN$595,451,FALSE),"-"))) -> 0.83077584 | J30: =IF($AF$14="2025",VLOOKUP($B30,GTMI_Groups!$B$2:$M$199,9,FALSE),IF($AF$14="2022",VLOOKUP((" "&$B30&" "),GTMI_Data!$B$2:$QN$595,452,FALSE),IF($AF$14="2020",VLOOKUP((" "&$B30&" "),GTMI_Data!$B$2:$QN$595,452,FALSE),"-"))) -> B | K30: =IF($AF$14="2025",VLOOKUP($B30,GTMI_Groups!$B$2:$M$199,10,FALSE),IF($AF$14="2022",VLOOKUP((" "&$B30&" "),GTMI_Data!$B$2:$QN$595,453,FALSE),IF($AF$14="2020",VLOOKUP((" "&$B30&" "),GTMI_Data!$B$2:$QN$595,453,FALSE),"-"))) -> 0.73796692 | L30: =IF($AF$14="2025",VLOOKUP($B30,GTMI_Groups!$B$2:$M$199,11,FALSE),IF($AF$14="2022",VLOOKUP((" "&$B30&" "),GTMI_Data!$B$2:$QN$595,454,FALSE),IF($AF$14="2020",VLOOKUP((" "&$B30&" "),GTMI_Data!$B$2:$QN$595,454,FALSE),"-"))) -> B | M30: =IF($AF$14="2025",VLOOKUP($B30,GTMI_Groups!$B$2:$M$199,12,FALSE),IF($AF$14="2022",VLOOKUP((" "&$B30&" "),GTMI_Data!$B$2:$QN$595,455,FALSE),IF($AF$14="2020",VLOOKUP((" "&$B30&" "),GTMI_Data!$B$2:$QN$595,455,FALSE),"-"))) -> 0.72547826 | N30: =IF($AF$14="2025",VLOOKUP($B30,GTMI_Data!$B$2:$PR$595,427,FALSE),IF($AF$14="2022",VLOOKUP((" "&$B30&" "),GTMI_Data!$B$2:$QN$595,427,FALSE),IF($AF$14="2020",VLOOKUP((" "&$B30&" "),GTMI_Data!$B$2:$QN$595,427,FALSE),"-"))) -> S | O30: =IF($AF$14="2025",VLOOKUP($B30,GTMI_Data!$B$2:$PR$595,428,FALSE),IF($AF$14="2022",VLOOKUP((" "&$B30&" "),GTMI_Data!$B$2:$QN$595,428,FALSE),IF($AF$14="2020",VLOOKUP((" "&$B30&" "),GTMI_Data!$B$2:$QN$595,428,FALSE),"-"))) -> AFR | P30: =IF($AF$14="2025",VLOOKUP($B30,GTMI_Data!$B$2:$PR$595,429,FALSE),IF($AF$14="2022",VLOOKUP((" "&$B30&" "),GTMI_Data!$B$2:$QN$595,429,FALSE),IF($AF$14="2020",VLOOKUP((" "&$B30&" "),GTMI_Data!$B$2:$QN$595,429,FALSE),"-"))) -> UM | Q30: =IF($AF$14="2025",VLOOKUP($B30,GTMI_Data!$B$2:$PR$595,430,FALSE),IF($AF$14="2022",VLOOKUP((" "&$B30&" "),GTMI_Data!$B$2:$QN$595,430,FALSE),IF($AF$14="2020",VLOOKUP((" "&$B30&" "),GTMI_Data!$B$2:$QN$595,430,FALSE),"-"))) -> - | R30: =IF($AF$14="2025",VLOOKUP($B30,GTMI_Data!$B$2:$PR$595,431,FALSE),IF($AF$14="2022",VLOOKUP((" "&$B30&" "),GTMI_Data!$B$2:$QN$595,431,FALSE),IF($AF$14="2020",VLOOKUP((" "&$B30&" "),GTMI_Data!$B$2:$QN$595,431,FALSE),"-"))) -> Blend | S30: =IF($AF$14="2025",VLOOKUP($B30,GTMI_Data!$B$2:$PR$595,432,FALSE),IF($AF$14="2022",VLOOKUP((" "&$B30&" "),GTMI_Data!$B$2:$QN$595,432,FALSE),IF($AF$14="2020",VLOOKUP((" "&$B30&" "),GTMI_Data!$B$2:$QN$595,432,FALSE),"-")))/1000 -> 0.522331 | T30: =IF($AF$14="2025",VLOOKUP($B30,GTMI_Data!$B$2:$PR$595,433,FALSE),IF($AF$14="2022",VLOOKUP((" "&$B30&" "),GTMI_Data!$B$2:$QN$595,433,FALSE),IF($AF$14="2020",VLOOKUP((" "&$B30&" "),GTMI_Data!$B$2:$QN$595,433,FALSE),"-"))) -> 0

Sheet Regions
A1: WBreg | B1: Code | C1: Economy > 2025 data | D1: I-1 | E1: I-2 | F1: I-3 | G1: I-4 | H1: I-5 | I1: I-6 | J1: I-7 | K1: I-8 | L1: I-9 | M1: I-10 | N1: I-11 | O1: I-12 | P1: I-13 | Q1: I-14 | R1: I-15 | S1: I-17 | T1: I-19
A2: AFE | B2: AGO | C2: Angola | D2: =VLOOKUP($B2,GTMI_Data!$B$2:$PK$595,D$200,FALSE) -> 0 | E2: =VLOOKUP($B2,GTMI_Data!$B$2:$PK$595,E$200,FALSE) -> 2 | F2: =VLOOKUP($B2,GTMI_Data!$B$2:$PK$595,F$200,FALSE) -> 2 | G2: =VLOOKUP($B2,GTMI_Data!$B$2:$PK$595,G$200,FALSE) -> 2 | H2: =VLOOKUP($B2,GTMI_Data!$B$2:$PK$595,H$200,FALSE) -> 2 | I2: =VLOOKUP($B2,GTMI_Data!$B$2:$PK$595,I$200,FALSE) -> 2 | J2: =VLOOKUP($B2,GTMI_Data!$B$2:$PK$595,J$200,FALSE) -> 2 | K2: =VLOOKUP($B2,GTMI_Data!$B$2:$PK$595,K$200,FALSE) -> 2 | ... T2: =VLOOKUP($B2,GTMI_Data!$B$2:$PK$595,T$200,FALSE) -> 2
A3: AFE | B3: BWA | C3: Botswana | D3: =VLOOKUP($B3,GTMI_Data!$B$2:$PK$595,D$200,FALSE) -> 0 | E3: =VLOOKUP($B3,GTMI_Data!$B$2:$PK$595,E$200,FALSE) -> 2 | F3: =VLOOKUP($B3,GTMI_Data!$B$2:$PK$595,F$200,FALSE) -> 1 | G3: =VLOOKUP($B3,GTMI_Data!$B$2:$PK$595,G$200,FALSE) -> 0 | H3: =VLOOKUP($B3,GTMI_Data!$B$2:$PK$595,H$200,FALSE) -> 2 | I3: =VLOOKUP($B3,GTMI_Data!$B$2:$PK$595,I$200,FALSE) -> 2 | J3: =VLOOKUP($B3,GTMI_Data!$B$2:$PK$595,J$200,FALSE) -> 2 | K3: =VLOOKUP($B3,GTMI_Data!$B$2:$PK$595,K$200,FALSE) -> 2 | ... T3: =VLOOKUP($B3,GTMI_Data!$B$2:$PK$595,T$200,FALSE) -> 2
A4: AFE | B4: BDI | C4: Burundi | D4: =VLOOKUP($B4,GTMI_Data!$B$2:$PK$595,D$200,FALSE) -> 1 | E4: =VLOOKUP($B4,GTMI_Data!$B$2:$PK$595,E$200,FALSE) -> 0 | F4: =VLOOKUP($B4,GTMI_Data!$B$2:$PK$595,F$200,FALSE) -> 0 | G4: =VLOOKUP($B4,GTMI_Data!$B$2:$PK$595,G$200,FALSE) -> 2 | H4: =VLOOKUP($B4,GTMI_Data!$B$2:$PK$595,H$200,FALSE) -> 2 | I4: =VLOOKUP($B4,GTMI_Data!$B$2:$PK$595,I$200,FALSE) -> 2 | J4: =VLOOKUP($B4,GTMI_Data!$B$2:$PK$595,J$200,FALSE) -> 2 | K4: =VLOOKUP($B4,GTMI_Data!$B$2:$PK$595,K$200,FALSE) -> 2 | ... T4: =VLOOKUP($B4,GTMI_Data!$B$2:$PK$595,T$200,FALSE) -> 0
A5: AFE | B5: COM | C5: Comoros | D5: =VLOOKUP($B5,GTMI_Data!$B$2:$PK$595,D$200,FALSE) -> 0 | E5: =VLOOKUP($B5,GTMI_Data!$B$2:$PK$595,E$200,FALSE) -> 2 | F5: =VLOOKUP($B5,GTMI_Data!$B$2:$PK$595,F$200,FALSE) -> 0 | G5: =VLOOKUP($B5,GTMI_Data!$B$2:$PK$595,G$200,FALSE) -> 1 | H5: =VLOOKUP($B5,GTMI_Data!$B$2:$PK$595,H$200,FALSE) -> 2 | I5: =VLOOKUP($B5,GTMI_Data!$B$2:$PK$595,I$200,FALSE) -> 0 | J5: =VLOOKUP($B5,GTMI_Data!$B$2:$PK$595,J$200,FALSE) -> 0 | K5: =VLOOKUP($B5,GTMI_Data!$B$2:$PK$595,K$200,FALSE) -> 2 | ... T5: =VLOOKUP($B5,GTMI_Data!$B$2:$PK$595,T$200,FALSE) -> 1
A6: AFE | B6: COD | C6: Congo, Dem. Rep. | D6: =VLOOKUP($B6,GTMI_Data!$B$2:$PK$595,D$200,FALSE) -> 0 | E6: =VLOOKUP($B6,GTMI_Data!$B$2:$PK$595,E$200,FALSE) -> 0 | F6: =VLOOKUP($B6,GTMI_Data!$B$2:$PK$595,F$200,FALSE) -> 0 | G6: =VLOOKUP($B6,GTMI_Data!$B$2:$PK$595,G$200,FALSE) -> 0 | H6: =VLOOKUP($B6,GTMI_Data!$B$2:$PK$595,H$200,FALSE) -> 2 | I6: =VLOOKUP($B6,GTMI_Data!$B$2:$PK$595,I$200,FALSE) -> 0 | J6: =VLOOKUP($B6,GTMI_Data!$B$2:$PK$595,J$200,FALSE) -> 2 | K6: =VLOOKUP($B6,GTMI_Data!$B$2:$PK$595,K$200,FALSE) -> 2 | ... T6: =VLOOKUP($B6,GTMI_Data!$B$2:$PK$595,T$200,FALSE) -> 0
A7: AFE | B7: ERI | C7: Eritrea | D7: =VLOOKUP($B7,GTMI_Data!$B$2:$PK$595,D$200,FALSE) -> 0 | E7: =VLOOKUP($B7,GTMI_Data!$B$2:$PK$595,E$200,FALSE) -> 0 | F7: =VLOOKUP($B7,GTMI_Data!$B$2:$PK$595,F$200,FALSE) -> 0 | G7: =VLOOKUP($B7,GTMI_Data!$B$2:$PK$595,G$200,FALSE) -> 0 | H7: =VLOOKUP($B7,GTMI_Data!$B$2:$PK$595,H$200,FALSE) -> 0 | I7: =VLOOKUP($B7,GTMI_Data!$B$2:$PK$595,I$200,FALSE) -> 0 | J7: =VLOOKUP($B7,GTMI_Data!$B$2:$PK$595,J$200,FALSE) -> 0 | K7: =VLOOKUP($B7,GTMI_Data!$B$2:$PK$595,K$200,FALSE) -> 2 | ... T7: =VLOOKUP($B7,GTMI_Data!$B$2:$PK$595,T$200,FALSE) -> 0
A8: AFE | B8: SWZ | C8: Eswatini | D8: =VLOOKUP($B8,GTMI_Data!$B$2:$PK$595,D$200,FALSE) -> 0 | E8: =VLOOKUP($B8,GTMI_Data!$B$2:$PK$595,E$200,FALSE) -> 0 | F8: =VLOOKUP($B8,GTMI_Data!$B$2:$PK$595,F$200,FALSE) -> 2 | G8: =VLOOKUP($B8,GTMI_Data!$B$2:$PK$595,G$200,FALSE) -> 0 | H8: =VLOOKUP($B8,GTMI_Data!$B$2:$PK$595,H$200,FALSE) -> 1 | I8: =VLOOKUP($B8,GTMI_Data!$B$2:$PK$595,I$200,FALSE) -> 1 | J8: =VLOOKUP($B8,GTMI_Data!$B$2:$PK$595,J$200,FALSE) -> 2 | K8: =VLOOKUP($B8,GTMI_Data!$B$2:$PK$595,K$200,FALSE) -> 2 | ... T8: =VLOOKUP($B8,GTMI_Data!$B$2:$PK$595,T$200,FALSE) -> 0
A9: AFE | B9: ETH | C9: Ethiopia | D9: =VLOOKUP($B9,GTMI_Data!$B$2:$PK$595,D$200,FALSE) -> 1 | E9: =VLOOKUP($B9,GTMI_Data!$B$2:$PK$595,E$200,FALSE) -> 2 | F9: =VLOOKUP($B9,GTMI_Data!$B$2:$PK$595,F$200,FALSE) -> 2 | G9: =VLOOKUP($B9,GTMI_Data!$B$2:$PK$595,G$200,FALSE) -> 0 | H9: =VLOOKUP($B9,GTMI_Data!$B$2:$PK$595,H$200,FALSE) -> 2 | I9: =VLOOKUP($B9,GTMI_Data!$B$2:$PK$595,I$200,FALSE) -> 2 | J9: =VLOOKUP($B9,GTMI_Data!$B$2:$PK$595,J$200,FALSE) -> 2 | K9: =VLOOKUP($B9,GTMI_Data!$B$2:$PK$595,K$200,FALSE) -> 2 | ... T9: =VLOOKUP($B9,GTMI_Data!$B$2:$PK$595,T$200,FALSE) -> 2
A10: AFE | B10: KEN | C10: Kenya | D10: =VLOOKUP($B10,GTMI_Data!$B$2:$PK$595,D$200,FALSE) -> 2 | E10: =VLOOKUP($B10,GTMI_Data!$B$2:$PK$595,E$200,FALSE) -> 2 | F10: =VLOOKUP($B10,GTMI_Data!$B$2:$PK$595,F$200,FALSE) -> 2 | G10: =VLOOKUP($B10,GTMI_Data!$B$2:$PK$595,G$200,FALSE) -> 1 | H10: =VLOOKUP($B10,GTMI_Data!$B$2:$PK$595,H$200,FALSE) -> 2 | I10: =VLOOKUP($B10,GTMI_Data!$B$2:$PK$595,I$200,FALSE) -> 2 | J10: =VLOOKUP($B10,GTMI_Data!$B$2:$PK$595,J$200,FALSE) -> 2 | K10: =VLOOKUP($B10,GTMI_Data!$B$2:$PK$595,K$200,FALSE) -> 2 | ... T10: =VLOOKUP($B10,GTMI_Data!$B$2:$PK$595,T$200,FALSE) -> 1
A11: AFE | B11: LSO | C11: Lesotho | D11: =VLOOKUP($B11,GTMI_Data!$B$2:$PK$595,D$200,FALSE) -> 0 | E11: =VLOOKUP($B11,GTMI_Data!$B$2:$PK$595,E$200,FALSE) -> 1 | F11: =VLOOKUP($B11,GTMI_Data!$B$2:$PK$595,F$200,FALSE) -> 1 | G11: =VLOOKUP($B11,GTMI_Data!$B$2:$PK$595,G$200,FALSE) -> 1 | H11: =VLOOKUP($B11,GTMI_Data!$B$2:$PK$595,H$200,FALSE) -> 2 | I11: =VLOOKUP($B11,GTMI_Data!$B$2:$PK$595,I$200,FALSE) -> 2 | J11: =VLOOKUP($B11,GTMI_Data!$B$2:$PK$595,J$200,FALSE) -> 2 | K11: =VLOOKUP($B11,GTMI_Data!$B$2:$PK$595,K$200,FALSE) -> 2 | ... T11: =VLOOKUP($B11,GTMI_Data!$B$2:$PK$595,T$200,FALSE) -> 1
A12: AFE | B12: MDG | C12: Madagascar | D12: =VLOOKUP($B12,GTMI_Data!$B$2:$PK$595,D$200,FALSE) -> 0 | E12: =VLOOKUP($B12,GTMI_Data!$B$2:$PK$595,E$200,FALSE) -> 0 | F12: =VLOOKUP($B12,GTMI_Data!$B$2:$PK$595,F$200,FALSE) -> 2 | G12: =VLOOKUP($B12,GTMI_Data!$B$2:$PK$595,G$200,FALSE) -> 2 | H12: =VLOOKUP($B12,GTMI_Data!$B$2:$PK$595,H$200,FALSE) -> 2 | I12: =VLOOKUP($B12,GTMI_Data!$B$2:$PK$595,I$200,FALSE) -> 2 | J12: =VLOOKUP($B12,GTMI_Data!$B$2:$PK$595,J$200,FALSE) -> 2 | K12: =VLOOKUP($B12,GTMI_Data!$B$2:$PK$595,K$200,FALSE) -> 2 | ... T12: =VLOOKUP($B12,GTMI_Data!$B$2:$PK$595,T$200,FALSE) -> 1
A13: AFE | B13: MWI | C13: Malawi | D13: =VLOOKUP($B13,GTMI_Data!$B$2:$PK$595,D$200,FALSE) -> 1 | E13: =VLOOKUP($B13,GTMI_Data!$B$2:$PK$595,E$200,FALSE) -> 1 | F13: =VLOOKUP($B13,GTMI_Data!$B$2:$PK$595,F$200,FALSE) -> 0 | G13: =VLOOKUP($B13,GTMI_Data!$B$2:$PK$595,G$200,FALSE) -> 2 | H13: =VLOOKUP($B13,GTMI_Data!$B$2:$PK$595,H$200,FALSE) -> 2 | I13: =VLOOKUP($B13,GTMI_Data!$B$2:$PK$595,I$200,FALSE) -> 2 | J13: =VLOOKUP($B13,GTMI_Data!$B$2:$PK$595,J$200,FALSE) -> 2 | K13: =VLOOKUP($B13,GTMI_Data!$B$2:$PK$595,K$200,FALSE) -> 2 | ... T13: =VLOOKUP($B13,GTMI_Data!$B$2:$PK$595,T$200,FALSE) -> 1
... A30: AFW | B30: CPV | C30: Cabo Verde | D30: =VLOOKUP($B30,GTMI_Data!$B$2:$PK$595,D$200,FALSE) -> 2 | E30: =VLOOKUP($B30,GTMI_Data!$B$2:$PK$595,E$200,FALSE) -> 2 | F30: =VLOOKUP($B30,GTMI_Data!$B$2:$PK$595,F$200,FALSE) -> 1 | G30: =VLOOKUP($B30,GTMI_Data!$B$2:$PK$595,G$200,FALSE) -> 2 | H30: =VLOOKUP($B30,GTMI_Data!$B$2:$PK$595,H$200,FALSE) -> 2 | I30: =VLOOKUP($B30,GTMI_Data!$B$2:$PK$595,I$200,FALSE) -> 2 | J30: =VLOOKUP($B30,GTMI_Data!$B$2:$PK$595,J$200,FALSE) -> 2 | K30: =VLOOKUP($B30,GTMI_Data!$B$2:$PK$595,K$200,FALSE) -> 2 | ... T30: =VLOOKUP($B30,GTMI_Data!$B$2:$PK$595,T$200,FALSE) -> 2

Sheet Trends
B1: Trends > | C1: =IF($C$2,"Diffusion of PFM institutions and Government systems (without small states)","Diffusion of PFM institutions and Government systems") -> Diffusion of PFM institutions and Government systems | M1: =$B$63 -> 2025
C2: FALSE
M3: Year | N3: FMIS | O3: F | P3: Trea | Q3: Tr | R3: TSA | S3: Ts | T3: Tax
M4: 1984 | N4: =IF($C$2,COUNTIFS(GTMI_Data!$BB$2:$BB$595,"<=1984",GTMI_Data!$AW$2:$AW$595,">0",GTMI_Data!$A$2:$A$595,$B$63,GTMI_Data!$PR$2:$PR$595,0),COUNTIFS(GTMI_Data!$BB$2:$BB$595,"<=1984",GTMI_Data!$AW$2:$AW$595,">0",GTMI_Data!$A$2:$A$595,$B$63)) -> 0 | O4: =N4 -> 0 | P4: =IF($C$2,COUNTIFS(GTMI_Data!$BP$2:$BP$595,"<=1984",GTMI_Data!$A$2:$A$595,$B$63,GTMI_Data!$PR$2:$PR$595,0),COUNTIFS(GTMI_Data!$BP$2:$BP$595,"<=1984",GTMI_Data!$A$2:$A$595,$B$63)) -> 107 | Q4: =P4 -> 107 | R4: =IF($C$2,COUNTIFS(GTMI_Data!$BR$2:$BR$595,"<=1984",GTMI_Data!$BN$2:$BN$595,">0",GTMI_Data!$A$2:$A$595,$B$63,GTMI_Data!$PR$2:$PR$595,0),COUNTIFS(GTMI_Data!$BR$2:$BR$595,"<=1984",GTMI_Data!$BN$2:$BN$595,">0",GTMI_Data!$A$2:$A$595,$B$63)) -> 16 | S4: =R4 -> 16 | T4: =IF($C$2,COUNTIFS(GTMI_Data!$CA$2:$CA$595,"<=1984",GTMI_Data!$A$2:$A$595,$B$63,GTMI_Data!$PR$2:$PR$595,0),COUNTIFS(GTMI_Data!$CA$2:$CA$595,"<=1984",GTMI_Data!$A$2:$A$595,$B$63)) -> 78
M5: 1985 | N5: =IF($C$2,COUNTIFS(GTMI_Data!$BB$2:$BB$595,$M5,GTMI_Data!$AW$2:$AW$595,">0",GTMI_Data!$A$2:$A$595,$B$63,GTMI_Data!$PR$2:$PR$595,0),COUNTIFS(GTMI_Data!$BB$2:$BB$595,$M5,GTMI_Data!$AW$2:$AW$595,">0",GTMI_Data!$A$2:$A$595,$B$63)) -> 0 | O5: =O4+N5 -> 0 | P5: =IF($C$2,COUNTIFS(GTMI_Data!$BP$2:$BP$595,$M5,GTMI_Data!$A$2:$A$595,$B$63,GTMI_Data!$PR$2:$PR$595,0),COUNTIFS(GTMI_Data!$BP$2:$BP$595,$M5,GTMI_Data!$A$2:$A$595,$B$63)) -> 1 | Q5: =Q4+P5 -> 108 | R5: =IF($C$2,COUNTIFS(GTMI_Data!$BR$2:$BR$595,$M5,GTMI_Data!$BN$2:$BN$595,">0",GTMI_Data!$A$2:$A$595,$B$63,GTMI_Data!$PR$2:$PR$595,0),COUNTIFS(GTMI_Data!$BR$2:$BR$595,$M5,GTMI_Data!$BN$2:$BN$595,">0",GTMI_Data!$A$2:$A$595,$B$63)) -> 2 | S5: =S4+R5 -> 18 | T5: =IF($C$2,COUNTIFS(GTMI_Data!$CA$2:$CA$595,$M5,GTMI_Data!$A$2:$A$595,$B$63,GTMI_Data!$PR$2:$PR$595,0),COUNTIFS(GTMI_Data!$CA$2:$CA$595,$M5,GTMI_Data!$A$2:$A$595,$B$63)) -> 0
M6: 1986 | N6: =IF($C$2,COUNTIFS(GTMI_Data!$BB$2:$BB$595,$M6,GTMI_Data!$AW$2:$AW$595,">0",GTMI_Data!$A$2:$A$595,$B$63,GTMI_Data!$PR$2:$PR$595,0),COUNTIFS(GTMI_Data!$BB$2:$BB$595,$M6,GTMI_Data!$AW$2:$AW$595,">0",GTMI_Data!$A$2:$A$595,$B$63)) -> 0 | O6: =O5+N6 -> 0 | P6: =IF($C$2,COUNTIFS(GTMI_Data!$BP$2:$BP$595,$M6,GTMI_Data!$A$2:$A$595,$B$63,GTMI_Data!$PR$2:$PR$595,0),COUNTIFS(GTMI_Data!$BP$2:$BP$595,$M6,GTMI_Data!$A$2:$A$595,$B$63)) -> 3 | Q6: =Q5+P6 -> 111 | R6: =IF($C$2,COUNTIFS(GTMI_Data!$BR$2:$BR$595,$M6,GTMI_Data!$BN$2:$BN$595,">0",GTMI_Data!$A$2:$A$595,$B$63,GTMI_Data!$PR$2:$PR$595,0),COUNTIFS(GTMI_Data!$BR$2:$BR$595,$M6,GTMI_Data!$BN$2:$BN$595,">0",GTMI_Data!$A$2:$A$595,$B$63)) -> 0 | S6: =S5+R6 -> 18 | T6: =IF($C$2,COUNTIFS(GTMI_Data!$CA$2:$CA$595,$M6,GTMI_Data!$A$2:$A$595,$B$63,GTMI_Data!$PR$2:$PR$595,0),COUNTIFS(GTMI_Data!$CA$2:$CA$595,$M6,GTMI_Data!$A$2:$A$595,$B$63)) -> 1
M7: 1987 | N7: =IF($C$2,COUNTIFS(GTMI_Data!$BB$2:$BB$595,$M7,GTMI_Data!$AW$2:$AW$595,">0",GTMI_Data!$A$2:$A$595,$B$63,GTMI_Data!$PR$2:$PR$595,0),COUNTIFS(GTMI_Data!$BB$2:$BB$595,$M7,GTMI_Data!$AW$2:$AW$595,">0",GTMI_Data!$A$2:$A$595,$B$63)) -> 1 | O7: =O6+N7 -> 1 | P7: =IF($C$2,COUNTIFS(GTMI_Data!$BP$2:$BP$595,$M7,GTMI_Data!$A$2:$A$595,$B$63,GTMI_Data!$PR$2:$PR$595,0),COUNTIFS(GTMI_Data!$BP$2:$BP$595,$M7,GTMI_Data!$A$2:$A$595,$B$63)) -> 1 | Q7: =Q6+P7 -> 112 | R7: =IF($C$2,COUNTIFS(GTMI_Data!$BR$2:$BR$595,$M7,GTMI_Data!$BN$2:$BN$595,">0",GTMI_Data!$A$2:$A$595,$B$63,GTMI_Data!$PR$2:$PR$595,0),COUNTIFS(GTMI_Data!$BR$2:$BR$595,$M7,GTMI_Data!$BN$2:$BN$595,">0",GTMI_Data!$A$2:$A$595,$B$63)) -> 1 | S7: =S6+R7 -> 19 | T7: =IF($C$2,COUNTIFS(GTMI_Data!$CA$2:$CA$595,$M7,GTMI_Data!$A$2:$A$595,$B$63,GTMI_Data!$PR$2:$PR$595,0),COUNTIFS(GTMI_Data!$CA$2:$CA$595,$M7,GTMI_Data!$A$2:$A$595,$B$63)) -> 0
M8: 1988 | N8: =IF($C$2,COUNTIFS(GTMI_Data!$BB$2:$BB$595,$M8,GTMI_Data!$AW$2:$AW$595,">0",GTMI_Data!$A$2:$A$595,$B$63,GTMI_Data!$PR$2:$PR$595,0),COUNTIFS(GTMI_Data!$BB$2:$BB$595,$M8,GTMI_Data!$AW$2:$AW$595,">0",GTMI_Data!$A$2:$A$595,$B$63)) -> 0 | O8: =O7+N8 -> 1 | P8: =IF($C$2,COUNTIFS(GTMI_Data!$BP$2:$BP$595,$M8,GTMI_Data!$A$2:$A$595,$B$63,GTMI_Data!$PR$2:$PR$595,0),COUNTIFS(GTMI_Data!$BP$2:$BP$595,$M8,GTMI_Data!$A$2:$A$595,$B$63)) -> 2 | Q8: =Q7+P8 -> 114 | R8: =IF($C$2,COUNTIFS(GTMI_Data!$BR$2:$BR$595,$M8,GTMI_Data!$BN$2:$BN$595,">0",GTMI_Data!$A$2:$A$595,$B$63,GTMI_Data!$PR$2:$PR$595,0),COUNTIFS(GTMI_Data!$BR$2:$BR$595,$M8,GTMI_Data!$BN$2:$BN$595,">0",GTMI_Data!$A$2:$A$595,$B$63)) -> 2 | S8: =S7+R8 -> 21 | T8: =IF($C$2,COUNTIFS(GTMI_Data!$CA$2:$CA$595,$M8,GTMI_Data!$A$2:$A$595,$B$63,GTMI_Data!$PR$2:$PR$595,0),COUNTIFS(GTMI_Data!$CA$2:$CA$595,$M8,GTMI_Data!$A$2:$A$595,$B$63)) -> 2
M9: 1989 | N9: =IF($C$2,COUNTIFS(GTMI_Data!$BB$2:$BB$595,$M9,GTMI_Data!$AW$2:$AW$595,">0",GTMI_Data!$A$2:$A$595,$B$63,GTMI_Data!$PR$2:$PR$595,0),COUNTIFS(GTMI_Data!$BB$2:$BB$595,$M9,GTMI_Data!$AW$2:$AW$595,">0",GTMI_Data!$A$2:$A$595,$B$63)) -> 0 | O9: =O8+N9 -> 1 | P9: =IF($C$2,COUNTIFS(GTMI_Data!$BP$2:$BP$595,$M9,GTMI_Data!$A$2:$A$595,$B$63,GTMI_Data!$PR$2:$PR$595,0),COUNTIFS(GTMI_Data!$BP$2:$BP$595,$M9,GTMI_Data!$A$2:$A$595,$B$63)) -> 1 | Q9: =Q8+P9 -> 115 | R9: =IF($C$2,COUNTIFS(GTMI_Data!$BR$2:$BR$595,$M9,GTMI_Data!$BN$2:$BN$595,">0",GTMI_Data!$A$2:$A$595,$B$63,GTMI_Data!$PR$2:$PR$595,0),COUNTIFS(GTMI_Data!$BR$2:$BR$595,$M9,GTMI_Data!$BN$2:$BN$595,">0",GTMI_Data!$A$2:$A$595,$B$63)) -> 2 | S9: =S8+R9 -> 23 | T9: =IF($C$2,COUNTIFS(GTMI_Data!$CA$2:$CA$595,$M9,GTMI_Data!$A$2:$A$595,$B$63,GTMI_Data!$PR$2:$PR$595,0),COUNTIFS(GTMI_Data!$CA$2:$CA$595,$M9,GTMI_Data!$A$2:$A$595,$B$63)) -> 2
M10: 1990 | N10: =IF($C$2,COUNTIFS(GTMI_Data!$BB$2:$BB$595,$M10,GTMI_Data!$AW$2:$AW$595,">0",GTMI_Data!$A$2:$A$595,$B$63,GTMI_Data!$PR$2:$PR$595,0),COUNTIFS(GTMI_Data!$BB$2:$BB$595,$M10,GTMI_Data!$AW$2:$AW$595,">0",GTMI_Data!$A$2:$A$595,$B$63)) -> 0 | O10: =O9+N10 -> 1 | P10: =IF($C$2,COUNTIFS(GTMI_Data!$BP$2:$BP$595,$M10,GTMI_Data!$A$2:$A$595,$B$63,GTMI_Data!$PR$2:$PR$595,0),COUNTIFS(GTMI_Data!$BP$2:$BP$595,$M10,GTMI_Data!$A$2:$A$595,$B$63)) -> 6 | Q10: =Q9+P10 -> 121 | R10: =IF($C$2,COUNTIFS(GTMI_Data!$BR$2:$BR$595,$M10,GTMI_Data!$BN$2:$BN$595,">0",GTMI_Data!$A$2:$A$595,$B$63,GTMI_Data!$PR$2:$PR$595,0),COUNTIFS(GTMI_Data!$BR$2:$BR$595,$M10,GTMI_Data!$BN$2:$BN$595,">0",GTMI_Data!$A$2:$A$595,$B$63)) -> 3 | S10: =S9+R10 -> 26 | T10: =IF($C$2,COUNTIFS(GTMI_Data!$CA$2:$CA$595,$M10,GTMI_Data!$A$2:$A$595,$B$63,GTMI_Data!$PR$2:$PR$595,0),COUNTIFS(GTMI_Data!$CA$2:$CA$595,$M10,GTMI_Data!$A$2:$A$595,$B$63)) -> 11
M11: 1991 | N11: =IF($C$2,COUNTIFS(GTMI_Data!$BB$2:$BB$595,$M11,GTMI_Data!$AW$2:$AW$595,">0",GTMI_Data!$A$2:$A$595,$B$63,GTMI_Data!$PR$2:$PR$595,0),COUNTIFS(GTMI_Data!$BB$2:$BB$595,$M11,GTMI_Data!$AW$2:$AW$595,">0",GTMI_Data!$A$2:$A$595,$B$63)) -> 0 | O11: =O10+N11 -> 1 | P11: =IF($C$2,COUNTIFS(GTMI_Data!$BP$2:$BP$595,$M11,GTMI_Data!$A$2:$A$595,$B$63,GTMI_Data!$PR$2:$PR$595,0),COUNTIFS(GTMI_Data!$BP$2:$BP$595,$M11,GTMI_Data!$A$2:$A$595,$B$63)) -> 4 | Q11: =Q10+P11 -> 125 | R11: =IF($C$2,COUNTIFS(GTMI_Data!$BR$2:$BR$595,$M11,GTMI_Data!$BN$2:$BN$595,">0",GTMI_Data!$A$2:$A$595,$B$63,GTMI_Data!$PR$2:$PR$595,0),COUNTIFS(GTMI_Data!$BR$2:$BR$595,$M11,GTMI_Data!$BN$2:$BN$595,">0",GTMI_Data!$A$2:$A$595,$B$63)) -> 0 | S11: =S10+R11 -> 26 | T11: =IF($C$2,COUNTIFS(GTMI_Data!$CA$2:$CA$595,$M11,GTMI_Data!$A$2:$A$595,$B$63,GTMI_Data!$PR$2:$PR$595,0),COUNTIFS(GTMI_Data!$CA$2:$CA$595,$M11,GTMI_Data!$A$2:$A$595,$B$63)) -> 7
M12: 1992 | N12: =IF($C$2,COUNTIFS(GTMI_Data!$BB$2:$BB$595,$M12,GTMI_Data!$AW$2:$AW$595,">0",GTMI_Data!$A$2:$A$595,$B$63,GTMI_Data!$PR$2:$PR$595,0),COUNTIFS(GTMI_Data!$BB$2:$BB$595,$M12,GTMI_Data!$AW$2:$AW$595,">0",GTMI_Data!$A$2:$A$595,$B$63)) -> 0 | O12: =O11+N12 -> 1 | P12: =IF($C$2,COUNTIFS(GTMI_Data!$BP$2:$BP$595,$M12,GTMI_Data!$A$2:$A$595,$B$63,GTMI_Data!$PR$2:$PR$595,0),COUNTIFS(GTMI_Data!$BP$2:$BP$595,$M12,GTMI_Data!$A$2:$A$595,$B$63)) -> 2 | Q12: =Q11+P12 -> 127 | R12: =IF($C$2,COUNTIFS(GTMI_Data!$BR$2:$BR$595,$M12,GTMI_Data!$BN$2:$BN$595,">0",GTMI_Data!$A$2:$A$595,$B$63,GTMI_Data!$PR$2:$PR$595,0),COUNTIFS(GTMI_Data!$BR$2:$BR$595,$M12,GTMI_Data!$BN$2:$BN$595,">0",GTMI_Data!$A$2:$A$595,$B$63)) -> 0 | S12: =S11+R12 -> 26 | T12: =IF($C$2,COUNTIFS(GTMI_Data!$CA$2:$CA$595,$M12,GTMI_Data!$A$2:$A$595,$B$63,GTMI_Data!$PR$2:$PR$595,0),COUNTIFS(GTMI_Data!$CA$2:$CA$595,$M12,GTMI_Data!$A$2:$A$595,$B$63)) -> 6
M13: 1993 | N13: =IF($C$2,COUNTIFS(GTMI_Data!$BB$2:$BB$595,$M13,GTMI_Data!$AW$2:$AW$595,">0",GTMI_Data!$A$2:$A$595,$B$63,GTMI_Data!$PR$2:$PR$595,0),COUNTIFS(GTMI_Data!$BB$2:$BB$595,$M13,GTMI_Data!$AW$2:$AW$595,">0",GTMI_Data!$A$2:$A$595,$B$63)) -> 0 | O13: =O12+N13 -> 1 | P13: =IF($C$2,COUNTIFS(GTMI_Data!$BP$2:$BP$595,$M13,GTMI_Data!$A$2:$A$595,$B$63,GTMI_Data!$PR$2:$PR$595,0),COUNTIFS(GTMI_Data!$BP$2:$BP$595,$M13,GTMI_Data!$A$2:$A$595,$B$63)) -> 5 | Q13: =Q12+P13 -> 132 | R13: =IF($C$2,COUNTIFS(GTMI_Data!$BR$2:$BR$595,$M13,GTMI_Data!$BN$2:$BN$595,">0",GTMI_Data!$A$2:$A$595,$B$63,GTMI_Data!$PR$2:$PR$595,0),COUNTIFS(GTMI_Data!$BR$2:$BR$595,$M13,GTMI_Data!$BN$2:$BN$595,">0",GTMI_Data!$A$2:$A$595,$B$63)) -> 1 | S13: =S12+R13 -> 27 | T13: =IF($C$2,COUNTIFS(GTMI_Data!$CA$2:$CA$595,$M13,GTMI_Data!$A$2:$A$595,$B$63,GTMI_Data!$PR$2:$PR$595,0),COUNTIFS(GTMI_Data!$CA$2:$CA$595,$M13,GTMI_Data!$A$2:$A$595,$B$63)) -> 3
M14: 1994 | N14: =IF($C$2,COUNTIFS(GTMI_Data!$BB$2:$BB$595,$M14,GTMI_Data!$AW$2:$AW$595,">0",GTMI_Data!$A$2:$A$595,$B$63,GTMI_Data!$PR$2:$PR$595,0),COUNTIFS(GTMI_Data!$BB$2:$BB$595,$M14,GTMI_Data!$AW$2:$AW$595,">0",GTMI_Data!$A$2:$A$595,$B$63)) -> 0 | O14: =O13+N14 -> 1 | P14: =IF($C$2,COUNTIFS(GTMI_Data!$BP$2:$BP$595,$M14,GTMI_Data!$A$2:$A$595,$B$63,GTMI_Data!$PR$2:$PR$595,0),COUNTIFS(GTMI_Data!$BP$2:$BP$595,$M14,GTMI_Data!$A$2:$A$595,$B$63)) -> 4 | Q14: =Q13+P14 -> 136 | R14: =IF($C$2,COUNTIFS(GTMI_Data!$BR$2:$BR$595,$M14,GTMI_Data!$BN$2:$BN$595,">0",GTMI_Data!$A$2:$A$595,$B$63,GTMI_Data!$PR$2:$PR$595,0),COUNTIFS(GTMI_Data!$BR$2:$BR$595,$M14,GTMI_Data!$BN$2:$BN$595,">0",GTMI_Data!$A$2:$A$595,$B$63)) -> 1 | S14: =S13+R14 -> 28 | T14: =IF($C$2,COUNTIFS(GTMI_Data!$CA$2:$CA$595,$M14,GTMI_Data!$A$2:$A$595,$B$63,GTMI_Data!$PR$2:$PR$595,0),COUNTIFS(GTMI_Data!$CA$2:$CA$595,$M14,GTMI_Data!$A$2:$A$595,$B$63)) -> 5
M15: 1995 | N15: =IF($C$2,COUNTIFS(GTMI_Data!$BB$2:$BB$595,$M15,GTMI_Data!$AW$2:$AW$595,">0",GTMI_Data!$A$2:$A$595,$B$63,GTMI_Data!$PR$2:$PR$595,0),COUNTIFS(GTMI_Data!$BB$2:$BB$595,$M15,GTMI_Data!$AW$2:$AW$595,">0",GTMI_Data!$A$2:$A$595,$B$63)) -> 2 | O15: =O14+N15 -> 3 | P15: =IF($C$2,COUNTIFS(GTMI_Data!$BP$2:$BP$595,$M15,GTMI_Data!$A$2:$A$595,$B$63,GTMI_Data!$PR$2:$PR$595,0),COUNTIFS(GTMI_Data!$BP$2:$BP$595,$M15,GTMI_Data!$A$2:$A$595,$B$63)) -> 7 | Q15: =Q14+P15 -> 143 | R15: =IF($C$2,COUNTIFS(GTMI_Data!$BR$2:$BR$595,$M15,GTMI_Data!$BN$2:$BN$595,">0",GTMI_Data!$A$2:$A$595,$B$63,GTMI_Data!$PR$2:$PR$595,0),COUNTIFS(GTMI_Data!$BR$2:$BR$595,$M15,GTMI_Data!$BN$2:$BN$595,">0",GTMI_Data!$A$2:$A$595,$B$63)) -> 3 | S15: =S14+R15 -> 31 | T15: =IF($C$2,COUNTIFS(GTMI_Data!$CA$2:$CA$595,$M15,GTMI_Data!$A$2:$A$595,$B$63,GTMI_Data!$PR$2:$PR$595,0),COUNTIFS(GTMI_Data!$CA$2:$CA$595,$M15,GTMI_Data!$A$2:$A$595,$B$63)) -> 5
M16: 1996 | N16: =IF($C$2,COUNTIFS(GTMI_Data!$BB$2:$BB$595,$M16,GTMI_Data!$AW$2:$AW$595,">0",GTMI_Data!$A$2:$A$595,$B$63,GTMI_Data!$PR$2:$PR$595,0),COUNTIFS(GTMI_Data!$BB$2:$BB$595,$M16,GTMI_Data!$AW$2:$AW$595,">0",GTMI_Data!$A$2:$A$595,$B$63)) -> 1 | O16: =O15+N16 -> 4 | P16: =IF($C$2,COUNTIFS(GTMI_Data!$BP$2:$BP$595,$M16,GTMI_Data!$A$2:$A$595,$B$63,GTMI_Data!$PR$2:$PR$595,0),COUNTIFS(GTMI_Data!$BP$2:$BP$595,$M16,GTMI_Data!$A$2:$A$595,$B$63)) -> 5 | Q16: =Q15+P16 -> 148 | R16: =IF($C$2,COUNTIFS(GTMI_Data!$BR$2:$BR$595,$M16,GTMI_Data!$BN$2:$BN$595,">0",GTMI_Data!$A$2:$A$595,$B$63,GTMI_Data!$PR$2:$PR$595,0),COUNTIFS(GTMI_Data!$BR$2:$BR$595,$M16,GTMI_Data!$BN$2:$BN$595,">0",GTMI_Data!$A$2:$A$595,$B$63)) -> 0 | S16: =S15+R16 -> 31 | T16: =IF($C$2,COUNTIFS(GTMI_Data!$CA$2:$CA$595,$M16,GTMI_Data!$A$2:$A$595,$B$63,GTMI_Data!$PR$2:$PR$595,0),COUNTIFS(GTMI_Data!$CA$2:$CA$595,$M16,GTMI_Data!$A$2:$A$595,$B$63)) -> 2
... M30: 2010 | N30: =IF($C$2,COUNTIFS(GTMI_Data!$BB$2:$BB$595,$M30,GTMI_Data!$AW$2:$AW$595,">0",GTMI_Data!$A$2:$A$595,$B$63,GTMI_Data!$PR$2:$PR$595,0),COUNTIFS(GTMI_Data!$BB$2:$BB$595,$M30,GTMI_Data!$AW$2:$AW$595,">0",GTMI_Data!$A$2:$A$595,$B$63)) -> 9 | O30: =O29+N30 -> 100 | P30: =IF($C$2,COUNTIFS(GTMI_Data!$BP$2:$BP$595,$M30,GTMI_Data!$A$2:$A$595,$B$63,GTMI_Data!$PR$2:$PR$595,0),COUNTIFS(GTMI_Data!$BP$2:$BP$595,$M30,GTMI_Data!$A$2:$A$595,$B$63)) -> 0 | Q30: =Q29+P30 -> 186 | R30: =IF($C$2,COUNTIFS(GTMI_Data!$BR$2:$BR$595,$M30,GTMI_Data!$BN$2:$BN$595,">0",GTMI_Data!$A$2:$A$595,$B$63,GTMI_Data!$PR$2:$PR$595,0),COUNTIFS(GTMI_Data!$BR$2:$BR$595,$M30,GTMI_Data!$BN$2:$BN$595,">0",GTMI_Data!$A$2:$A$595,$B$63)) -> 6 | S30: =S29+R30 -> 115 | T30: =IF($C$2,COUNTIFS(GTMI_Data!$CA$2:$CA$595,$M30,GTMI_Data!$A$2:$A$595,$B$63,GTMI_Data!$PR$2:$PR$595,0),COUNTIFS(GTMI_Data!$CA$2:$CA$595,$M30,GTMI_Data!$A$2:$A$595,$B$63)) -> 5

Sheet Metadata
A1: # | B1: 2025 GTMI Indicators & Sub-indicators | C1: Response options & Data format | D1: Please select a country name | F1: Year | I1: 9 | J1: =IF(J2=1,2020,IF(J2=2,2022,2025)) -> 2025
A2: Economy | B2: Country name | C2: =VLOOKUP(I2,Economies!B2:C199,2,FALSE) -> Australia | F2: =IF(I3="S","CG GTMI Survey Data","Remotely collected data") -> CG GTMI Survey Data | I2: =VLOOKUP($I$1,Economies!$A$2:$C$199,2,FALSE) -> AUS | J2: 3
A3: I-1 | B3: Is there a shared cloud platform available for all government entities? | C3: 0= No, 1= Only cloud strategy/policy (no platform yet), 2= Yes (platform in use) | D3: =IFERROR(VLOOKUP($I$5,GTMI_Data!$B$2:$PR$595,ROW(),FALSE),"-") -> 2 | I3: =IFERROR(VLOOKUP($I$2,GTMI_Data!$B$2:$QD$595,427,FALSE),"-") -> S | J3: 2020
A4: I-1.1 | B4: Name of the Government Cloud platform | C4: Text | D4: =IFERROR(VLOOKUP($I$5,GTMI_Data!$B$2:$PR$595,ROW(),FALSE),"-") -> Secure Cloud Strategy | I4: =VLOOKUP($I$1,Economies!$A$2:$C$199,3,FALSE) -> Australia | J4: 2022
A5: I-1.2 | B5: Cloud platform / strategy URL | C5: URL | D5: =IFERROR(VLOOKUP($I$5,GTMI_Data!$B$2:$PR$595,ROW(),FALSE),"-") -> https://architecture.digital.gov.au/secure-cloud-strategy | I5: =IF(J2=1," "&I2&" ",IF(J2=2," "&I2&" ",I2)) -> AUS | J5: 2025
A6: I-1.3 | B6: Government Cloud was launched / will be launched in (year) | C6: YYYY | D6: =IFERROR(VLOOKUP($I$5,GTMI_Data!$B$2:$PR$595,ROW(),FALSE),"-") -> 2018
A7: I-1.4 | B7: Type of cloud platform established | C7: 0= Unknown, 1= Public (Commercial), 2= Private (Government), 3= Hybrid | D7: =IFERROR(VLOOKUP($I$5,GTMI_Data!$B$2:$PR$595,ROW(),FALSE),"-") -> 3
A8: I-1.5 | B8: Official name of the entity operating the Government Cloud platform | C8: Text | D8: =IFERROR(VLOOKUP($I$5,GTMI_Data!$B$2:$PR$595,ROW(),FALSE),"-") -> Digital Transformation Agency (DTA)
A9: I-1.6 | B9: Government Cloud data hosting policy? | C9: 0= No policy / Unknown, 1= Keeping data inside the country, 2= Keeping data outside the country, 3= Hybrid (inside + outside) | D9: =IFERROR(VLOOKUP($I$5,GTMI_Data!$B$2:$PR$595,ROW(),FALSE),"-") -> 3
A10: I-1.6.1 | B10: If Yes (there is a cloud hosting policy) > Supporting document (report / URL) | C10: Enter URL (public link) or Attach relevant report | D10: =IFERROR(VLOOKUP($I$5,GTMI_Data!$B$2:$PR$595,ROW(),FALSE),"-") -> https://www.hostingcertification.gov.au/
A11: I-1.7 | B11: Cloud services provided | C11: 0= Unknown, 1= SaaS, 2= PaaS, 3= IaaS, 4= XaaS | D11: =IFERROR(VLOOKUP($I$5,GTMI_Data!$B$2:$PR$595,ROW(),FALSE),"-") -> 4
A12: I-1.8 | B12: Is there one shared Government Cloud platform or several? | C12: 0= Unknown, 1= Several cloud platforms (Central/Local levels), 2= One shared cloud platform | D12: =IFERROR(VLOOKUP($I$5,GTMI_Data!$B$2:$PR$595,ROW(),FALSE),"-") -> 1
A13: I-1.9 | B13: Are government agencies actively using the cloud platform? | C13: 0= No / Unknown, 1= Yes | D13: =IFERROR(VLOOKUP($I$5,GTMI_Data!$B$2:$PR$595,ROW(),FALSE),"-") -> 1
A14: I-1.9.1 | B14: If Yes > How would you rate the extent of cloud platform utilization? | C14: 1= Minimal, 2= Moderate, 3= Significant, 4= Extensive | D14: =IFERROR(VLOOKUP($I$5,GTMI_Data!$B$2:$PR$595,ROW(),FALSE),"-") -> 4
A15: I-1.9.2 | B15: If Yes > Relevant document / web page (URL) | C15: Enter URL (public link) or Attach relevant document | D15: =IFERROR(VLOOKUP($I$5,GTMI_Data!$B$2:$PR$595,ROW(),FALSE),"-") -> https://www.digital.gov.au/sites/default/files/documents/2025-03/2025%20Major%20Digital%20Projects%20Report.pdf
A16: I-2 | B16: Is there a government enterprise architecture framework? | C16: 0= No, 1= In draft / Planned, 2= Yes | D16: =IFERROR(VLOOKUP($I$5,GTMI_Data!$B$2:$PR$595,ROW(),FALSE),"-") -> 2
A17: I-2.1 | B17: Name of the GEA framework | C17: Text | D17: =IFERROR(VLOOKUP($I$5,GTMI_Data!$B$2:$PR$595,ROW(),FALSE),"-") -> Australian Government Architecture
... A30: I-3.3 | B30: GIF was introduced / will be introduced in (year) | C30: YYYY | D30: =IFERROR(VLOOKUP($I$5,GTMI_Data!$B$2:$PR$595,ROW(),FALSE),"-") -> 2019

Sheet External
A1: 2024 UN EGDI | E1: I-27 | F1: I-18 | G1: I-44 | H1: I-16 | J1: 2024 ITU GCI | M1: I-43
A2: Code | B2: Country Name | C2: E-Gov Rank | D2: E-Gov Index | E2: E-Particip Index | F2: Online Service Index | G2: Human Capital Index | H2: Telecom Infra Index | J2: Code | K2: Economy | L2: GCI Tier | M2: GCI | N2: Legal Measures | O2: Technical | P2: Organizational | Q2: Capacity Development | R2: Cooperation
A3: AFG | B3: Afghanistan | C3: 188 | D3: 0.20827 | E3: 0.1096 | F3: 0.14379 | G3: 0.2643 | H3: 0.21672 | J3: AFG | K3: Afghanistan | L3: T5 | M3: =SUM(N3:R3) -> 18.41 | N3: 5.81 | O3: 3.29 | P3: 6.99 | Q3: 2.32 | R3: 0
A4: ALB | B4: Albania | C4: 62 | D4: 0.8 | E4: 0.726 | F4: 0.81441 | G4: 0.81059 | H4: 0.77497 | J4: ALB | K4: Albania | L4: T2 | M4: =SUM(N4:R4) -> 86.51 | N4: 20 | O4: 18.38 | P4: 19.47 | Q4: 12.08 | R4: 16.58
A5: DZA | B5: Algeria | C5: 116 | D5: 0.59556 | E5: 0.0548 | F5: 0.332 | G5: 0.64179 | H5: 0.8129 | J5: DZA | K5: Algeria | L5: T3 | M5: =SUM(N5:R5) -> 65.87 | N5: 19.18 | O5: 8.57 | P5: 11.02 | Q5: 13.91 | R5: 13.19
A6: AND | B6: Andorra | C6: 88 | D6: 0.68931 | E6: 0.5479 | F6: 0.47804 | G6: 0.66684 | H6: 0.92307 | J6: AND | K6: Andorra | L6: T3 | M6: =SUM(N6:R6) -> 76.66 | N6: 18.04 | O6: 15.3 | P6: 13.88 | Q6: 11.74 | R6: 17.7
A7: AGO | B7: Angola | C7: 156 | D7: 0.41487 | E7: 0.2192 | F7: 0.39624 | G7: 0.47602 | H7: 0.37238 | J7: AGO | K7: Angola | L7: T4 | M7: =SUM(N7:R7) -> 39.49 | N7: 13.67 | O7: 1.78 | P7: 5.8 | Q7: 2.91 | R7: 15.33
A8: ATG | B8: Antigua and Barbuda | C8: 105 | D8: 0.64282 | E8: 0.3425 | F8: 0.41658 | G8: 0.71757 | H8: 0.79426 | J8: ATG | K8: Antigua and Barbuda | L8: T5 | M8: =SUM(N8:R8) -> 18.19 | N8: 11.84 | O8: 0 | P8: 0 | Q8: 2.36 | R8: 3.99
A9: ARG | B9: Argentina | C9: 42 | D9: 0.85733 | E9: 0.6301 | F9: 0.79649 | G9: 0.93298 | H9: 0.84254 | J9: ARG | K9: Argentina | L9: T4 | M9: =SUM(N9:R9) -> 51.51 | N9: 16.96 | O9: 12.18 | P9: 12.08 | Q9: 1.88 | R9: 8.41
A10: ARM | B10: Armenia | C10: 48 | D10: 0.84217 | E10: 0.8493 | F10: 0.7922 | G10: 0.8561 | H10: 0.87824 | J10: ARM | K10: Armenia | L10: T4 | M10: =SUM(N10:R10) -> 53.82 | N10: 17.22 | O10: 8.69 | P10: 2.81 | Q10: 10.35 | R10: 14.75
A11: AUS | B11: Australia | C11: 8 | D11: 0.9577 | E11: 0.863 | F11: 0.92219 | G11: 1 | H11: 0.95092 | J11: AUS | K11: Australia | L11: T1 | M11: =SUM(N11:R11) -> 96.24 | N11: 20 | O11: 17.95 | P11: 20 | Q11: 19.44 | R11: 18.85
A12: AUT | B12: Austria | C12: 22 | D12: 0.90653 | E12: 0.7808 | F12: 0.83829 | G12: 0.90028 | H12: 0.98096 | J12: AUT | K12: Austria | L12: T2 | M12: =SUM(N12:R12) -> 89.16 | N12: 18.42 | O12: 18.23 | P12: 17.56 | Q12: 18.36 | R12: 16.59
A13: AZE | B13: Azerbaijan | C13: 74 | D13: 0.76073 | E13: 0.4932 | F13: 0.73863 | G13: 0.72329 | H13: 0.82034 | J13: AZE | K13: Azerbaijan | L13: T2 | M13: =SUM(N13:R13) -> 93.76 | N13: 20 | O13: 18.02 | P13: 18.05 | Q13: 17.69 | R13: 20
A14: BHS | B14: Bahamas | C14: 83 | D14: 0.71434 | E14: 0.3151 | F14: 0.54021 | G14: 0.73762 | H14: 0.86522 | J14: BHS | K14: Bahamas | L14: T4 | M14: =SUM(N14:R14) -> 34 | N14: 11.26 | O14: 3.22 | P14: 5.47 | Q14: 6.08 | R14: 7.97
... A30: BDI | B30: Burundi | C30: 183 | D30: 0.24805 | E30: 0.2192 | F30: 0.3146 | G30: 0.39655 | H30: 0.03305 | J30: BDI | K30: Burundi | L30: T5 | M30: =SUM(N30:R30) -> 16.77 | N30: 9.9 | O30: 0 | P30: 0 | Q30: 1.03 | R30: 5.84

Sheet Economies
A1: # | B1: Code | C1: Economy | D1: Code | E1: # | F1: FCS | H1: # | I1: Code | J1: Country | K1: FCS | L1: FY25 FCS Status | N1: # | O1: Code | P1: Country | Q1: FCS | R1: FY23 FCS Status | T1: #
A2: 1 | B2: AFG | C2: Afghanistan | D2: AFG | E2: 1 | F2: =IFERROR(VLOOKUP(B2,$I$2:$K$40,3,FALSE),"-") -> FCS-1 | H2: 1 | I2: =VLOOKUP(J2,$C$2:$D$199,2,FALSE) -> AFG | J2: Afghanistan | K2: FCS-1 | L2: Conflict | N2: 1 | O2: =VLOOKUP(P2,$C$2:$D$199,2,FALSE) -> AFG | P2: Afghanistan | Q2: FCS-1 | R2: Conflict | T2: 1
A3: 2 | B3: ALB | C3: Albania | D3: ALB | E3: 2 | F3: =IFERROR(VLOOKUP(B3,$I$2:$K$40,3,FALSE),"-") -> - | H3: 2 | I3: =VLOOKUP(J3,$C$2:$D$199,2,FALSE) -> BFA | J3: Burkina Faso | K3: FCS-1 | L3: Conflict | N3: 2 | O3: =VLOOKUP(P3,$C$2:$D$199,2,FALSE) -> BFA | P3: Burkina Faso | Q3: FCS-1 | R3: Conflict | T3: 2
A4: 3 | B4: DZA | C4: Algeria | D4: DZA | E4: 3 | F4: =IFERROR(VLOOKUP(B4,$I$2:$K$40,3,FALSE),"-") -> - | H4: 3 | I4: =VLOOKUP(J4,$C$2:$D$199,2,FALSE) -> BDI | J4: Burundi | K4: FCS-2 | L4: Institutional and social fragility | N4: 3 | O4: =VLOOKUP(P4,$C$2:$D$199,2,FALSE) -> BDI | P4: Burundi | Q4: FCS-2 | R4: Institutional and social fragility | T4: 3
A5: 4 | B5: AND | C5: Andorra | D5: AND | E5: 4 | F5: =IFERROR(VLOOKUP(B5,$I$2:$K$40,3,FALSE),"-") -> - | H5: 4 | I5: =VLOOKUP(J5,$C$2:$D$199,2,FALSE) -> CMR | J5: Cameroon | K5: FCS-1 | L5: Conflict | N5: 4 | O5: =VLOOKUP(P5,$C$2:$D$199,2,FALSE) -> CMR | P5: Cameroon | Q5: FCS-1 | R5: Conflict | T5: 4
A6: 5 | B6: AGO | C6: Angola | D6: AGO | E6: 5 | F6: =IFERROR(VLOOKUP(B6,$I$2:$K$40,3,FALSE),"-") -> - | H6: 5 | I6: =VLOOKUP(J6,$C$2:$D$199,2,FALSE) -> CAF | J6: Central African Republic | K6: FCS-1 | L6: Conflict | N6: 5 | O6: =VLOOKUP(P6,$C$2:$D$199,2,FALSE) -> CAF | P6: Central African Republic | Q6: FCS-1 | R6: Conflict | T6: 5
A7: 6 | B7: ATG | C7: Antigua and Barbuda | D7: ATG | E7: 6 | F7: =IFERROR(VLOOKUP(B7,$I$2:$K$40,3,FALSE),"-") -> - | H7: 6 | I7: =VLOOKUP(J7,$C$2:$D$199,2,FALSE) -> TCD | J7: Chad | K7: FCS-2 | L7: Institutional and social fragility | N7: 6 | O7: =VLOOKUP(P7,$C$2:$D$199,2,FALSE) -> TCD | P7: Chad | Q7: FCS-2 | R7: Institutional and social fragility | T7: 6
A8: 7 | B8: ARG | C8: Argentina | D8: ARG | E8: 7 | F8: =IFERROR(VLOOKUP(B8,$I$2:$K$40,3,FALSE),"-") -> - | H8: 7 | I8: =VLOOKUP(J8,$C$2:$D$199,2,FALSE) -> COM | J8: Comoros | K8: FCS-2 | L8: Institutional and social fragility | N8: 7 | O8: =VLOOKUP(P8,$C$2:$D$199,2,FALSE) -> COM | P8: Comoros | Q8: FCS-2 | R8: Institutional and social fragility | T8: 7
A9: 8 | B9: ARM | C9: Armenia | D9: ARM | E9: 8 | F9: =IFERROR(VLOOKUP(B9,$I$2:$K$40,3,FALSE),"-") -> - | H9: 8 | I9: =VLOOKUP(J9,$C$2:$D$199,2,FALSE) -> COD | J9: Congo, Dem. Rep. | K9: FCS-1 | L9: Conflict | N9: 8 | O9: =VLOOKUP(P9,$C$2:$D$199,2,FALSE) -> COD | P9: Congo, Dem. Rep. | Q9: FCS-1 | R9: Conflict | T9: 8
A10: 9 | B10: AUS | C10: Australia | D10: AUS | E10: 9 | F10: =IFERROR(VLOOKUP(B10,$I$2:$K$40,3,FALSE),"-") -> - | H10: 9 | I10: =VLOOKUP(J10,$C$2:$D$199,2,FALSE) -> COG | J10: Congo, Rep. | K10: FCS-2 | L10: Institutional and social fragility | N10: 9 | O10: =VLOOKUP(P10,$C$2:$D$199,2,FALSE) -> COG | P10: Congo, Rep. | Q10: FCS-2 | R10: Institutional and social fragility | T10: 9
A11: 10 | B11: AUT | C11: Austria | D11: AUT | E11: 10 | F11: =IFERROR(VLOOKUP(B11,$I$2:$K$40,3,FALSE),"-") -> - | H11: 10 | I11: =VLOOKUP(J11,$C$2:$D$199,2,FALSE) -> ERI | J11: Eritrea | K11: FCS-2 | L11: Institutional and social fragility | N11: 10 | O11: =VLOOKUP(P11,$C$2:$D$199,2,FALSE) -> ERI | P11: Eritrea | Q11: FCS-2 | R11: Institutional and social fragility | T11: 10
A12: 11 | B12: AZE | C12: Azerbaijan | D12: AZE | E12: 11 | F12: =IFERROR(VLOOKUP(B12,$I$2:$K$40,3,FALSE),"-") -> - | H12: 11 | I12: =VLOOKUP(J12,$C$2:$D$199,2,FALSE) -> ETH | J12: Ethiopia | K12: FCS-1 | L12: Conflict | N12: 11 | O12: =VLOOKUP(P12,$C$2:$D$199,2,FALSE) -> ETH | P12: Ethiopia | Q12: FCS-1 | R12: Conflict | T12: 11
A13: 12 | B13: BHS | C13: Bahamas | D13: BHS | E13: 12 | F13: =IFERROR(VLOOKUP(B13,$I$2:$K$40,3,FALSE),"-") -> - | H13: 12 | I13: =VLOOKUP(J13,$C$2:$D$199,2,FALSE) -> GNB | J13: Guinea-Bissau | K13: FCS-2 | L13: Institutional and social fragility | N13: 12 | O13: =VLOOKUP(P13,$C$2:$D$199,2,FALSE) -> GNB | P13: Guinea-Bissau | Q13: FCS-2 | R13: Institutional and social fragility | T13: 12
... A30: 29 | B30: CPV | C30: Cabo Verde | D30: CPV | E30: 29 | F30: =IFERROR(VLOOKUP(B30,$I$2:$K$40,3,FALSE),"-") -> - | H30: 29 | I30: =VLOOKUP(J30,$C$2:$D$199,2,FALSE) -> SOM | J30: Somalia | K30: FCS-1 | L30: Conflict | N30: 29 | O30: =VLOOKUP(P30,$C$2:$D$199,2,FALSE) -> SDN | P30: Sudan | Q30: FCS-2 | R30: Institutional and social fragility | T30: 29
